{"notification":{"id":"6a48eae6-e433-4b23-9fc3-9563a8af995e","taskId":"6821a7ee80fdff20d64752f0","taskName":"Réalisation de l’Avant Projet Sommaire","projectName":"Construction d’un immeuble résidentiel","projectId":null,"phaseName":"Conception architecturale","phaseId":null,"message":"nouveaux modifications dans : Réalisation de l’Avant Projet Sommaire (Phase Conception architecturale) du Projet Construction d’un immeuble résidentiel","commentDate":"2025-06-12T00:35:26.658499405","notificationType":"tache","userIdsToNotify":["50da8c53-f1bb-47cb-9d06-b31e55706ed8","35d2c0ea-879b-4b68-9755-0e338f78bb28"],"commentContent":null,"commentAuthor":null,"actionType":"UPDATE"},"read":false,"sentByEmail":false,"timestamp":1749681326820}