{
    "sourceFile": ".env",
    "activeCommit": 0,
    "commits": [
        {
            "activePatchIndex": 50,
            "patches": [
                {
                    "date": 1748453006030,
                    "content": "Index: \n===================================================================\n--- \n+++ \n"
                },
                {
                    "date": 1748453013879,
                    "content": "Index: \n===================================================================\n--- \n+++ \n@@ -1,5 +1,5 @@\n-CLIENT_ID=272700212454-9s5a11um6udgkmpgiin3j0mngvbua4pa.apps.googleusercontent.com\r\n-CLIENT_SECRET=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\r\n+CLIENT_ID=\"272700212454-9s5a11um6udgkmpgiin3j0mngvbua4pa.apps.googleusercontent.com\"\r\n+CLIENT_SECRET=\"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\"\r\n REDIRECT_URI=http://localhost:3000/auth/google/callback\r\n FRONTEND_URL=http://localhost:3001\r\n PORT=3000\n\\ No newline at end of file\n"
                },
                {
                    "date": 1748453025939,
                    "content": "Index: \n===================================================================\n--- \n+++ \n@@ -1,5 +1,5 @@\n CLIENT_ID=\"272700212454-9s5a11um6udgkmpgiin3j0mngvbua4pa.apps.googleusercontent.com\"\r\n CLIENT_SECRET=\"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\"\r\n-REDIRECT_URI=http://localhost:3000/auth/google/callback\r\n-FRONTEND_URL=http://localhost:3001\r\n+REDIRECT_URI=\"http://localhost:3000/auth/google/callback\"\r\n+FRONTEND_URL=http://localhost:4200\r\n PORT=3000\n\\ No newline at end of file\n"
                },
                {
                    "date": 1748541313098,
                    "content": "Index: \n===================================================================\n--- \n+++ \n@@ -1,5 +1,5 @@\n CLIENT_ID=\"272700212454-9s5a11um6udgkmpgiin3j0mngvbua4pa.apps.googleusercontent.com\"\r\n CLIENT_SECRET=\"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\"\r\n REDIRECT_URI=\"http://localhost:3000/auth/google/callback\"\r\n-FRONTEND_URL=http://localhost:4200\r\n-PORT=3000\n\\ No newline at end of file\n+FRONTEND_URL=\"http://localhost:4200\"\r\n+PO\n\\ No newline at end of file\n"
                },
                {
                    "date": 1748541329624,
                    "content": "Index: \n===================================================================\n--- \n+++ \n@@ -1,5 +1,8 @@\n CLIENT_ID=\"272700212454-9s5a11um6udgkmpgiin3j0mngvbua4pa.apps.googleusercontent.com\"\r\n CLIENT_SECRET=\"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\"\r\n-REDIRECT_URI=\"http://localhost:3000/auth/google/callback\"\r\n+REDIRECT_URI=\"http://localhost:8079/auth/google/callback\"\r\n FRONTEND_URL=\"http://localhost:4200\"\r\n\\ No newline at end of file\n-PO\n+PORT=3000\r\n+\r\n+APP_NAME=EmailService\r\n+SERVER_PORT=8079\n\\ No newline at end of file\n"
                },
                {
                    "date": 1748541335511,
                    "content": "Index: \n===================================================================\n--- \n+++ \n@@ -1,7 +1,7 @@\n CLIENT_ID=\"272700212454-9s5a11um6udgkmpgiin3j0mngvbua4pa.apps.googleusercontent.com\"\r\n CLIENT_SECRET=\"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\"\r\n-REDIRECT_URI=\"http://localhost:8079/auth/google/callback\"\r\n+REDIRECT_URI=\"http://localhost:3000/auth/google/callback\"\r\n FRONTEND_URL=\"http://localhost:4200\"\r\n PORT=3000\r\n \r\n APP_NAME=EmailService\r\n"
                },
                {
                    "date": 1748541341769,
                    "content": "Index: \n===================================================================\n--- \n+++ \n@@ -4,5 +4,5 @@\n FRONTEND_URL=\"http://localhost:4200\"\r\n PORT=3000\r\n \r\n APP_NAME=EmailService\r\n-SERVER_PORT=8079\n\\ No newline at end of file\n+SERVER_PORT=8079\r\n"
                },
                {
                    "date": 1748541356164,
                    "content": "Index: \n===================================================================\n--- \n+++ \n@@ -5,4 +5,16 @@\n PORT=3000\r\n \r\n APP_NAME=EmailService\r\n SERVER_PORT=8079\r\n+\r\n+# Keycloak/OAuth\r\n+KEYCLOAK_ISSUER_URI=https://esmm.systeo.tn/realms/systeodigital\r\n+KEYCLOAK_JWKS_URI=https://esmm.systeo.tn/realms/systeodigital/protocol/openid-connect/certs\r\n+KEYCLOAK_AUDIENCE=app-projectPFE\r\n+KEYCLOAK_CLIENT_ID=app-projectPFE\r\n+KEYCLOAK_CLIENT_SECRET=5FfaiB11tLGbFcuwcgUZYgj0OaeYIaUX\r\n+KEYCLOAK_AUTH_SERVER_URL=https://esmm.systeo.tn\r\n+\r\n+# Eureka\r\n+EUREKA_INSTANCE_HOSTNAME=e8.systeo.tn\r\n+EUREKA_SERVICE_URL=https://eureka.systeo.tn/eureka/\n\\ No newline at end of file\n"
                },
                {
                    "date": 1748541452002,
                    "content": "Index: \n===================================================================\n--- \n+++ \n@@ -1,10 +1,9 @@\n CLIENT_ID=\"272700212454-9s5a11um6udgkmpgiin3j0mngvbua4pa.apps.googleusercontent.com\"\r\n CLIENT_SECRET=\"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\"\r\n REDIRECT_URI=\"http://localhost:3000/auth/google/callback\"\r\n FRONTEND_URL=\"http://localhost:4200\"\r\n-PORT=3000\r\n-\r\n+=\r\n APP_NAME=EmailService\r\n SERVER_PORT=8079\r\n \r\n # Keycloak/OAuth\r\n"
                },
                {
                    "date": 1748543102267,
                    "content": "Index: \n===================================================================\n--- \n+++ \n@@ -1,11 +1,11 @@\n CLIENT_ID=\"272700212454-9s5a11um6udgkmpgiin3j0mngvbua4pa.apps.googleusercontent.com\"\r\n CLIENT_SECRET=\"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\"\r\n-REDIRECT_URI=\"http://localhost:3000/auth/google/callback\"\r\n+REDIRECT_URI=\"http://localhost:8079/auth/google/callback\"\r\n FRONTEND_URL=\"http://localhost:4200\"\r\n =\r\n APP_NAME=EmailService\r\n-SERVER_PORT=8079\r\n+PORT=8079\r\n \r\n # Keycloak/OAuth\r\n KEYCLOAK_ISSUER_URI=https://esmm.systeo.tn/realms/systeodigital\r\n KEYCLOAK_JWKS_URI=https://esmm.systeo.tn/realms/systeodigital/protocol/openid-connect/certs\r\n"
                },
                {
                    "date": 1748543115423,
                    "content": "Index: \n===================================================================\n--- \n+++ \n@@ -3,9 +3,9 @@\n REDIRECT_URI=\"http://localhost:8079/auth/google/callback\"\r\n FRONTEND_URL=\"http://localhost:4200\"\r\n =\r\n APP_NAME=EmailService\r\n-PORT=8079\r\n+SERVER_PORT=8079\r\n \r\n # Keycloak/OAuth\r\n KEYCLOAK_ISSUER_URI=https://esmm.systeo.tn/realms/systeodigital\r\n KEYCLOAK_JWKS_URI=https://esmm.systeo.tn/realms/systeodigital/protocol/openid-connect/certs\r\n"
                },
                {
                    "date": 1748545618605,
                    "content": "Index: \n===================================================================\n--- \n+++ \n@@ -1,11 +1,11 @@\n CLIENT_ID=\"272700212454-9s5a11um6udgkmpgiin3j0mngvbua4pa.apps.googleusercontent.com\"\r\n CLIENT_SECRET=\"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\"\r\n REDIRECT_URI=\"http://localhost:8079/auth/google/callback\"\r\n FRONTEND_URL=\"http://localhost:4200\"\r\n-=\r\n+\r\n APP_NAME=EmailService\r\n-SERVER_PORT=8079\r\n+PORT=8079\r\n \r\n # Keycloak/OAuth\r\n KEYCLOAK_ISSUER_URI=https://esmm.systeo.tn/realms/systeodigital\r\n KEYCLOAK_JWKS_URI=https://esmm.systeo.tn/realms/systeodigital/protocol/openid-connect/certs\r\n"
                },
                {
                    "date": 1748545624569,
                    "content": "Index: \n===================================================================\n--- \n+++ \n@@ -4,9 +4,9 @@\n FRONTEND_URL=\"http://localhost:4200\"\r\n \r\n APP_NAME=EmailService\r\n PORT=8079\r\n-\r\n+NODE_ENV=development\r\n # Keycloak/OAuth\r\n KEYCLOAK_ISSUER_URI=https://esmm.systeo.tn/realms/systeodigital\r\n KEYCLOAK_JWKS_URI=https://esmm.systeo.tn/realms/systeodigital/protocol/openid-connect/certs\r\n KEYCLOAK_AUDIENCE=app-projectPFE\r\n"
                },
                {
                    "date": 1748545641164,
                    "content": "Index: \n===================================================================\n--- \n+++ \n@@ -5,15 +5,10 @@\n \r\n APP_NAME=EmailService\r\n PORT=8079\r\n NODE_ENV=development\r\n-# Keycloak/OAuth\r\n-KEYCLOAK_ISSUER_URI=https://esmm.systeo.tn/realms/systeodigital\r\n-KEYCLOAK_JWKS_URI=https://esmm.systeo.tn/realms/systeodigital/protocol/openid-connect/certs\r\n-KEYCLOAK_AUDIENCE=app-projectPFE\r\n-KEYCLOAK_CLIENT_ID=app-projectPFE\r\n-KEYCLOAK_CLIENT_SECRET=5FfaiB11tLGbFcuwcgUZYgj0OaeYIaUX\r\n-KEYCLOAK_AUTH_SERVER_URL=https://esmm.systeo.tn\r\n \r\n-# Eureka\r\n+\r\n+# Eureka Configuration\r\n EUREKA_INSTANCE_HOSTNAME=e8.systeo.tn\r\n+EUREKA_PREFER_IP_ADDRESS=false\r\n EUREKA_SERVICE_URL=https://eureka.systeo.tn/eureka/\n\\ No newline at end of file\n"
                },
                {
                    "date": 1748545650195,
                    "content": "Index: \n===================================================================\n--- \n+++ \n@@ -10,5 +10,9 @@\n \r\n # Eureka Configuration\r\n EUREKA_INSTANCE_HOSTNAME=e8.systeo.tn\r\n EUREKA_PREFER_IP_ADDRESS=false\r\n-EUREKA_SERVICE_URL=https://eureka.systeo.tn/eureka/\n\\ No newline at end of file\n+EUREKA_SERVICE_URL=https://eureka.systeo.tn/eureka/\r\n+\r\n+# Security\r\n+CORS_ENABLED=true\r\n+CORS_ORIGIN=*\n\\ No newline at end of file\n"
                },
                {
                    "date": 1748546307367,
                    "content": "Index: \n===================================================================\n--- \n+++ \n@@ -8,9 +8,9 @@\n NODE_ENV=development\r\n \r\n \r\n # Eureka Configuration\r\n-EUREKA_INSTANCE_HOSTNAME=e8.systeo.tn\r\n+EUREKA_INSTANCE_HOSTNAME=\"e8.systeo.tn\"\r\n EUREKA_PREFER_IP_ADDRESS=false\r\n EUREKA_SERVICE_URL=https://eureka.systeo.tn/eureka/\r\n \r\n # Security\r\n"
                },
                {
                    "date": 1748546314477,
                    "content": "Index: \n===================================================================\n--- \n+++ \n@@ -2,17 +2,17 @@\n CLIENT_SECRET=\"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\"\r\n REDIRECT_URI=\"http://localhost:8079/auth/google/callback\"\r\n FRONTEND_URL=\"http://localhost:4200\"\r\n \r\n-APP_NAME=EmailService\r\n+APP_NAME=\"EmailService\"\r\n PORT=8079\r\n NODE_ENV=development\r\n \r\n \r\n # Eureka Configuration\r\n EUREKA_INSTANCE_HOSTNAME=\"e8.systeo.tn\"\r\n EUREKA_PREFER_IP_ADDRESS=false\r\n-EUREKA_SERVICE_URL=https://eureka.systeo.tn/eureka/\r\n+EUREKA_SERVICE_URL=\"https://eureka.systeo.tn/eureka/\"\r\n \r\n # Security\r\n CORS_ENABLED=true\r\n CORS_ORIGIN=*\n\\ No newline at end of file\n"
                },
                {
                    "date": 1748549359353,
                    "content": "Index: \n===================================================================\n--- \n+++ \n@@ -9,10 +9,10 @@\n \r\n \r\n # Eureka Configuration\r\n EUREKA_INSTANCE_HOSTNAME=\"e8.systeo.tn\"\r\n-EUREKA_PREFER_IP_ADDRESS=false\r\n-EUREKA_SERVICE_URL=\"https://eureka.systeo.tn/eureka/\"\r\n+EUREKA_PREFER_IP=false \r\n+EUREKA_URL=\"https://eureka.systeo.tn/eureka/\"\r\n \r\n # Security\r\n CORS_ENABLED=true\r\n CORS_ORIGIN=*\n\\ No newline at end of file\n"
                },
                {
                    "date": 1748549369456,
                    "content": "Index: \n===================================================================\n--- \n+++ \n@@ -8,9 +8,10 @@\n NODE_ENV=development\r\n \r\n \r\n # Eureka Configuration\r\n-EUREKA_INSTANCE_HOSTNAME=\"e8.systeo.tn\"\r\n+EUREKA_ENABLED=true \r\n+EUREKA_HOSTNAME=\"e8.systeo.tn\"\r\n EUREKA_PREFER_IP=false \r\n EUREKA_URL=\"https://eureka.systeo.tn/eureka/\"\r\n \r\n # Security\r\n"
                },
                {
                    "date": 1748549378001,
                    "content": "Index: \n===================================================================\n--- \n+++ \n@@ -4,9 +4,8 @@\n FRONTEND_URL=\"http://localhost:4200\"\r\n \r\n APP_NAME=\"EmailService\"\r\n PORT=8079\r\n-NODE_ENV=development\r\n \r\n \r\n # Eureka Configuration\r\n EUREKA_ENABLED=true \r\n"
                },
                {
                    "date": 1748549984462,
                    "content": "Index: \n===================================================================\n--- \n+++ \n@@ -2,17 +2,18 @@\n CLIENT_SECRET=\"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\"\r\n REDIRECT_URI=\"http://localhost:8079/auth/google/callback\"\r\n FRONTEND_URL=\"http://localhost:4200\"\r\n \r\n-APP_NAME=\"EmailService\"\r\n+A# Application Configuration\r\n+APP_NAME=EmailService\r\n PORT=8079\r\n+NODE_ENV=development\r\n \r\n-\r\n # Eureka Configuration\r\n-EUREKA_ENABLED=true \r\n-EUREKA_HOSTNAME=\"e8.systeo.tn\"\r\n-EUREKA_PREFER_IP=false \r\n-EUREKA_URL=\"https://eureka.systeo.tn/eureka/\"\r\n+EUREKA_ENABLED=true\r\n+EUREKA_INSTANCE_HOSTNAME=e8.systeo.tn\r\n+EUREKA_PREFER_IP=false\r\n+EUREKA_SERVICE_URL=https://eureka.systeo.tn/eureka/\r\n \r\n # Security\r\n CORS_ENABLED=true\r\n CORS_ORIGIN=*\n\\ No newline at end of file\n"
                },
                {
                    "date": 1748549990463,
                    "content": "Index: \n===================================================================\n--- \n+++ \n@@ -3,12 +3,12 @@\n REDIRECT_URI=\"http://localhost:8079/auth/google/callback\"\r\n FRONTEND_URL=\"http://localhost:4200\"\r\n \r\n A# Application Configuration\r\n-APP_NAME=EmailService\r\n+APP_NAME=\"EmailService\"\r\n PORT=8079\r\n-NODE_ENV=development\r\n \r\n+\r\n # Eureka Configuration\r\n EUREKA_ENABLED=true\r\n EUREKA_INSTANCE_HOSTNAME=e8.systeo.tn\r\n EUREKA_PREFER_IP=false\r\n"
                },
                {
                    "date": 1748549996063,
                    "content": "Index: \n===================================================================\n--- \n+++ \n@@ -9,9 +9,9 @@\n \r\n \r\n # Eureka Configuration\r\n EUREKA_ENABLED=true\r\n-EUREKA_INSTANCE_HOSTNAME=e8.systeo.tn\r\n+EUREKA_INSTANCE_HOSTNAME=\"e8.systeo.tn\"\r\n EUREKA_PREFER_IP=false\r\n EUREKA_SERVICE_URL=https://eureka.systeo.tn/eureka/\r\n \r\n # Security\r\n"
                },
                {
                    "date": 1748550002038,
                    "content": "Index: \n===================================================================\n--- \n+++ \n@@ -3,15 +3,15 @@\n REDIRECT_URI=\"http://localhost:8079/auth/google/callback\"\r\n FRONTEND_URL=\"http://localhost:4200\"\r\n \r\n A# Application Configuration\r\n-APP_NAME=\"EmailService\"\r\n+APP_NAME=EmailService\r\n PORT=8079\r\n+NODE_ENV=development\r\n \r\n-\r\n # Eureka Configuration\r\n EUREKA_ENABLED=true\r\n-EUREKA_INSTANCE_HOSTNAME=\"e8.systeo.tn\"\r\n+EUREKA_INSTANCE_HOSTNAME=e8.systeo.tn\r\n EUREKA_PREFER_IP=false\r\n EUREKA_SERVICE_URL=https://eureka.systeo.tn/eureka/\r\n \r\n # Security\r\n"
                },
                {
                    "date": 1748564714791,
                    "content": "Index: \n===================================================================\n--- \n+++ \n@@ -1,7 +1,7 @@\n CLIENT_ID=\"272700212454-9s5a11um6udgkmpgiin3j0mngvbua4pa.apps.googleusercontent.com\"\r\n CLIENT_SECRET=\"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\"\r\n-REDIRECT_URI=\"http://localhost:8079/auth/google/callback\"\r\n+REDIRECT_URI=\"ya29.a0AW4Xtxh1tEIqgPWL2EJPGjn42lXdsomjTA0i5rXcpRhcpdDyBX48F6twoHjvyG6xxruH5gLRaJpjyVSZjn_niedsafdpjHCaUwyqEzKtH1gseiOlImKOjMwcNP2JW7cupva-VuhR730Z-Ja4qEH-PxCEOAzjkzKU891nGG-gaCgYKAV0SARUSFQHGX2MibUY94WKMOVU8vEarzLYdHw0175/auth/google/callback\"\r\n FRONTEND_URL=\"http://localhost:4200\"\r\n \r\n A# Application Configuration\r\n APP_NAME=EmailService\r\n"
                },
                {
                    "date": 1748564736767,
                    "content": "Index: \n===================================================================\n--- \n+++ \n@@ -1,7 +1,7 @@\n CLIENT_ID=\"272700212454-9s5a11um6udgkmpgiin3j0mngvbua4pa.apps.googleusercontent.com\"\r\n CLIENT_SECRET=\"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\"\r\n-REDIRECT_URI=\"ya29.a0AW4Xtxh1tEIqgPWL2EJPGjn42lXdsomjTA0i5rXcpRhcpdDyBX48F6twoHjvyG6xxruH5gLRaJpjyVSZjn_niedsafdpjHCaUwyqEzKtH1gseiOlImKOjMwcNP2JW7cupva-VuhR730Z-Ja4qEH-PxCEOAzjkzKU891nGG-gaCgYKAV0SARUSFQHGX2MibUY94WKMOVU8vEarzLYdHw0175/auth/google/callback\"\r\n+REDIRECT_URI=\"https://e8.systeo.tn/auth/google/callback\"\r\n FRONTEND_URL=\"http://localhost:4200\"\r\n \r\n A# Application Configuration\r\n APP_NAME=EmailService\r\n"
                },
                {
                    "date": 1748633202942,
                    "content": "Index: \n===================================================================\n--- \n+++ \n@@ -13,7 +13,4 @@\n EUREKA_INSTANCE_HOSTNAME=e8.systeo.tn\r\n EUREKA_PREFER_IP=false\r\n EUREKA_SERVICE_URL=https://eureka.systeo.tn/eureka/\r\n \r\n-# Security\r\n-CORS_ENABLED=true\r\n-CORS_ORIGIN=*\n\\ No newline at end of file\n"
                },
                {
                    "date": 1749216900566,
                    "content": "Index: \n===================================================================\n--- \n+++ \n@@ -13,4 +13,9 @@\n EUREKA_INSTANCE_HOSTNAME=e8.systeo.tn\r\n EUREKA_PREFER_IP=false\r\n EUREKA_SERVICE_URL=https://eureka.systeo.tn/eureka/\r\n \r\n+# RabbitMQ\r\n+RABBITMQ_URL=amqp://username:password@rabbitmq-host:5672\r\n+RABBITMQ_EXCHANGE=exchange.NotificationService.sendEmail\r\n+RABBITMQ_QUEUE=queue.EmailService.sendEmail\r\n+RABBITMQ_ROUTING_KEY=NotificationService.envoye.EmailService\n\\ No newline at end of file\n"
                },
                {
                    "date": 1749216907509,
                    "content": "Index: \n===================================================================\n--- \n+++ \n@@ -14,8 +14,8 @@\n EUREKA_PREFER_IP=false\r\n EUREKA_SERVICE_URL=https://eureka.systeo.tn/eureka/\r\n \r\n # RabbitMQ\r\n-RABBITMQ_URL=amqp://username:password@rabbitmq-host:5672\r\n+RABBITMQ_URL=amqp://admin:admin@rabbitmq-host:5672\r\n RABBITMQ_EXCHANGE=exchange.NotificationService.sendEmail\r\n RABBITMQ_QUEUE=queue.EmailService.sendEmail\r\n RABBITMQ_ROUTING_KEY=NotificationService.envoye.EmailService\n\\ No newline at end of file\n"
                },
                {
                    "date": 1749218489009,
                    "content": "Index: \n===================================================================\n--- \n+++ \n@@ -13,9 +13,12 @@\n EUREKA_INSTANCE_HOSTNAME=e8.systeo.tn\r\n EUREKA_PREFER_IP=false\r\n EUREKA_SERVICE_URL=https://eureka.systeo.tn/eureka/\r\n \r\n-# RabbitMQ\r\n-RABBITMQ_URL=amqp://admin:admin@rabbitmq-host:5672\r\n+# RabbitMQ Configuration\r\n+RABBITMQ_HOST=161.97.88.195\r\n+RABBITMQ_PORT=5672\r\n+RABBITMQ_USER=admin\r\n+RABBITMQ_PASS=admin\r\n RABBITMQ_EXCHANGE=exchange.NotificationService.sendEmail\r\n RABBITMQ_QUEUE=queue.EmailService.sendEmail\r\n RABBITMQ_ROUTING_KEY=NotificationService.envoye.EmailService\n\\ No newline at end of file\n"
                },
                {
                    "date": 1749291004003,
                    "content": "Index: \n===================================================================\n--- \n+++ \n@@ -20,5 +20,6 @@\n RABBITMQ_USER=admin\r\n RABBITMQ_PASS=admin\r\n RABBITMQ_EXCHANGE=exchange.NotificationService.sendEmail\r\n RABBITMQ_QUEUE=queue.EmailService.sendEmail\r\n-RABBITMQ_ROUTING_KEY=NotificationService.envoye.EmailService\n\\ No newline at end of file\n+RABBITMQ_ROUTING_KEY=NotificationService.envoye.EmailService\r\n+\r\n"
                },
                {
                    "date": 1749291009957,
                    "content": "Index: \n===================================================================\n--- \n+++ \n@@ -22,4 +22,5 @@\n RABBITMQ_EXCHANGE=exchange.NotificationService.sendEmail\r\n RABBITMQ_QUEUE=queue.EmailService.sendEmail\r\n RABBITMQ_ROUTING_KEY=NotificationService.envoye.EmailService\r\n \r\n+SYSTEM_EMAIL_USER_ID=\"archimanage@archimanage\"\n\\ No newline at end of file\n"
                },
                {
                    "date": 1749291016471,
                    "content": "Index: \n===================================================================\n--- \n+++ \n@@ -22,5 +22,5 @@\n RABBITMQ_EXCHANGE=exchange.NotificationService.sendEmail\r\n RABBITMQ_QUEUE=queue.EmailService.sendEmail\r\n RABBITMQ_ROUTING_KEY=NotificationService.envoye.EmailService\r\n \r\n-SYSTEM_EMAIL_USER_ID=\"archimanage@archimanage\"\n\\ No newline at end of file\n+SYSTEM_EMAIL_USER_ID=\"archimanagesysteo@@archimanage\"\n\\ No newline at end of file\n"
                },
                {
                    "date": 1749291022706,
                    "content": "Index: \n===================================================================\n--- \n+++ \n@@ -22,5 +22,5 @@\n RABBITMQ_EXCHANGE=exchange.NotificationService.sendEmail\r\n RABBITMQ_QUEUE=queue.EmailService.sendEmail\r\n RABBITMQ_ROUTING_KEY=NotificationService.envoye.EmailService\r\n \r\n-SYSTEM_EMAIL_USER_ID=\"archimanagesysteo@@archimanage\"\n\\ No newline at end of file\n+SYSTEM_EMAIL_USER_ID=\"archimanagesysteo@gmail.com@archimanage\"\n\\ No newline at end of file\n"
                },
                {
                    "date": 1749291033943,
                    "content": "Index: \n===================================================================\n--- \n+++ \n@@ -22,5 +22,5 @@\n RABBITMQ_EXCHANGE=exchange.NotificationService.sendEmail\r\n RABBITMQ_QUEUE=queue.EmailService.sendEmail\r\n RABBITMQ_ROUTING_KEY=NotificationService.envoye.EmailService\r\n \r\n-SYSTEM_EMAIL_USER_ID=\"archimanagesysteo@gmail.com@archimanage\"\n\\ No newline at end of file\n+SYSTEM_EMAIL_USER_ID=\"archimanage.systeo@gmail.comarchimanage\"\n\\ No newline at end of file\n"
                },
                {
                    "date": 1749292200290,
                    "content": "Index: \n===================================================================\n--- \n+++ \n@@ -20,7 +20,5 @@\n RABBITMQ_USER=admin\r\n RABBITMQ_PASS=admin\r\n RABBITMQ_EXCHANGE=exchange.NotificationService.sendEmail\r\n RABBITMQ_QUEUE=queue.EmailService.sendEmail\r\n-RABBITMQ_ROUTING_KEY=NotificationService.envoye.EmailService\r\n-\r\n-SYSTEM_EMAIL_USER_ID=\"archimanage.systeo@gmail.comarchimanage\"\n\\ No newline at end of file\n+RABBITMQ_ROUTING_KEY=NotificationService.envoye.EmailService\n\\ No newline at end of file\n"
                },
                {
                    "date": 1749293467363,
                    "content": "Index: \n===================================================================\n--- \n+++ \n@@ -1,7 +1,7 @@\n CLIENT_ID=\"272700212454-9s5a11um6udgkmpgiin3j0mngvbua4pa.apps.googleusercontent.com\"\r\n CLIENT_SECRET=\"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\"\r\n-REDIRECT_URI=\"https://e8.systeo.tn/auth/google/callback\"\r\n+REDIRECT_URI=\"https:///auth/google/callback\"\r\n FRONTEND_URL=\"http://localhost:4200\"\r\n \r\n A# Application Configuration\r\n APP_NAME=EmailService\r\n"
                },
                {
                    "date": 1749293472710,
                    "content": "Index: \n===================================================================\n--- \n+++ \n@@ -1,7 +1,7 @@\n CLIENT_ID=\"272700212454-9s5a11um6udgkmpgiin3j0mngvbua4pa.apps.googleusercontent.com\"\r\n CLIENT_SECRET=\"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\"\r\n-REDIRECT_URI=\"https:///auth/google/callback\"\r\n+REDIRECT_URI=\"http://localhost/auth/google/callback\"\r\n FRONTEND_URL=\"http://localhost:4200\"\r\n \r\n A# Application Configuration\r\n APP_NAME=EmailService\r\n"
                },
                {
                    "date": 1749296261869,
                    "content": "Index: \n===================================================================\n--- \n+++ \n@@ -1,7 +1,7 @@\n CLIENT_ID=\"272700212454-9s5a11um6udgkmpgiin3j0mngvbua4pa.apps.googleusercontent.com\"\r\n CLIENT_SECRET=\"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\"\r\n-REDIRECT_URI=\"http://localhost/auth/google/callback\"\r\n+REDIRECT_URI=\"http://localhost:8079/auth/google/callback\"\r\n FRONTEND_URL=\"http://localhost:4200\"\r\n \r\n A# Application Configuration\r\n APP_NAME=EmailService\r\n@@ -20,5 +20,6 @@\n RABBITMQ_USER=admin\r\n RABBITMQ_PASS=admin\r\n RABBITMQ_EXCHANGE=exchange.NotificationService.sendEmail\r\n RABBITMQ_QUEUE=queue.EmailService.sendEmail\r\n-RABBITMQ_ROUTING_KEY=NotificationService.envoye.EmailService\n\\ No newline at end of file\n+RABBITMQ_ROUTING_KEY=NotificationService.envoye.EmailService\r\n+\r\n"
                },
                {
                    "date": 1749303118254,
                    "content": "Index: \n===================================================================\n--- \n+++ \n@@ -1,9 +1,9 @@\n CLIENT_ID=\"272700212454-9s5a11um6udgkmpgiin3j0mngvbua4pa.apps.googleusercontent.com\"\r\n CLIENT_SECRET=\"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\"\r\n REDIRECT_URI=\"http://localhost:8079/auth/google/callback\"\r\n FRONTEND_URL=\"http://localhost:4200\"\r\n-\r\n+'1//09oB7A4YVsXO1CgYIARAAGAkSNwF-L9IrWlUOUnaPEybbg8OGHXVmdVTqr70WiFMoMSK-8xP349d9rFBJtifwTSXogpc-DILO35M'\r\n A# Application Configuration\r\n APP_NAME=EmailService\r\n PORT=8079\r\n NODE_ENV=development\r\n@@ -22,4 +22,5 @@\n RABBITMQ_EXCHANGE=exchange.NotificationService.sendEmail\r\n RABBITMQ_QUEUE=queue.EmailService.sendEmail\r\n RABBITMQ_ROUTING_KEY=NotificationService.envoye.EmailService\r\n \r\n+SYSTEM_EMAIL=\"archimanage.systeo@gmail.com\"\n\\ No newline at end of file\n"
                },
                {
                    "date": 1749303129800,
                    "content": "Index: \n===================================================================\n--- \n+++ \n@@ -1,9 +1,9 @@\n CLIENT_ID=\"272700212454-9s5a11um6udgkmpgiin3j0mngvbua4pa.apps.googleusercontent.com\"\r\n CLIENT_SECRET=\"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\"\r\n REDIRECT_URI=\"http://localhost:8079/auth/google/callback\"\r\n FRONTEND_URL=\"http://localhost:4200\"\r\n-'1//09oB7A4YVsXO1CgYIARAAGAkSNwF-L9IrWlUOUnaPEybbg8OGHXVmdVTqr70WiFMoMSK-8xP349d9rFBJtifwTSXogpc-DILO35M'\r\n+GOOGLE_SYSTEM_REFRESH_TOKEN'1//09oB7A4YVsXO1CgYIARAAGAkSNwF-L9IrWlUOUnaPEybbg8OGHXVmdVTqr70WiFMoMSK-8xP349d9rFBJtifwTSXogpc-DILO35M'\r\n A# Application Configuration\r\n APP_NAME=EmailService\r\n PORT=8079\r\n NODE_ENV=development\r\n"
                },
                {
                    "date": 1749391661359,
                    "content": "Index: \n===================================================================\n--- \n+++ \n@@ -1,13 +1,13 @@\n CLIENT_ID=\"272700212454-9s5a11um6udgkmpgiin3j0mngvbua4pa.apps.googleusercontent.com\"\r\n CLIENT_SECRET=\"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\"\r\n REDIRECT_URI=\"http://localhost:8079/auth/google/callback\"\r\n FRONTEND_URL=\"http://localhost:4200\"\r\n-GOOGLE_SYSTEM_REFRESH_TOKEN'1//09oB7A4YVsXO1CgYIARAAGAkSNwF-L9IrWlUOUnaPEybbg8OGHXVmdVTqr70WiFMoMSK-8xP349d9rFBJtifwTSXogpc-DILO35M'\r\n+GOOGLE_SYSTEM_REFRESH_TOKEN='1//09oB7A4YVsXO1CgYIARAAGAkSNwF-L9IrWlUOUnaPEybbg8OGHXVmdVTqr70WiFMoMSK-8xP349d9rFBJtifwTSXogpc-DILO35M'\r\n A# Application Configuration\r\n APP_NAME=EmailService\r\n PORT=8079\r\n-NODE_ENV=development\r\n+#NODE_ENV=development\r\n \r\n # Eureka Configuration\r\n EUREKA_ENABLED=true\r\n EUREKA_INSTANCE_HOSTNAME=e8.systeo.tn\r\n"
                },
                {
                    "date": 1749593476020,
                    "content": "Index: \n===================================================================\n--- \n+++ \n@@ -1,12 +1,12 @@\n CLIENT_ID=\"272700212454-9s5a11um6udgkmpgiin3j0mngvbua4pa.apps.googleusercontent.com\"\r\n CLIENT_SECRET=\"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\"\r\n-REDIRECT_URI=\"http://localhost:8079/auth/google/callback\"\r\n+REDIRECT_URI=\"http://localhost:8069/auth/google/callback\"\r\n FRONTEND_URL=\"http://localhost:4200\"\r\n GOOGLE_SYSTEM_REFRESH_TOKEN='1//09oB7A4YVsXO1CgYIARAAGAkSNwF-L9IrWlUOUnaPEybbg8OGHXVmdVTqr70WiFMoMSK-8xP349d9rFBJtifwTSXogpc-DILO35M'\r\n A# Application Configuration\r\n APP_NAME=EmailService\r\n-PORT=8079\r\n+PORT=8069\r\n #NODE_ENV=development\r\n \r\n # Eureka Configuration\r\n EUREKA_ENABLED=true\r\n@@ -22,5 +22,5 @@\n RABBITMQ_EXCHANGE=exchange.NotificationService.sendEmail\r\n RABBITMQ_QUEUE=queue.EmailService.sendEmail\r\n RABBITMQ_ROUTING_KEY=NotificationService.envoye.EmailService\r\n \r\n-SYSTEM_EMAIL=\"archimanage.systeo@gmail.com\"\n\\ No newline at end of file\n+SYSTEM_EMAIL=\"archimanage.systeo@gmail.com\"\r\n"
                },
                {
                    "date": 1749629978784,
                    "content": "Index: \n===================================================================\n--- \n+++ \n@@ -1,10 +1,10 @@\n CLIENT_ID=\"272700212454-9s5a11um6udgkmpgiin3j0mngvbua4pa.apps.googleusercontent.com\"\r\n CLIENT_SECRET=\"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\"\r\n REDIRECT_URI=\"http://localhost:8069/auth/google/callback\"\r\n-FRONTEND_URL=\"http://localhost:4200\"\r\n+FRONTEND_URL=\"https://localhost:4200\"\r\n GOOGLE_SYSTEM_REFRESH_TOKEN='1//09oB7A4YVsXO1CgYIARAAGAkSNwF-L9IrWlUOUnaPEybbg8OGHXVmdVTqr70WiFMoMSK-8xP349d9rFBJtifwTSXogpc-DILO35M'\r\n-A# Application Configuration\r\n+# Application Configuration\r\n APP_NAME=EmailService\r\n PORT=8069\r\n #NODE_ENV=development\r\n \r\n"
                },
                {
                    "date": 1749629989935,
                    "content": "Index: \n===================================================================\n--- \n+++ \n@@ -1,8 +1,8 @@\n CLIENT_ID=\"272700212454-9s5a11um6udgkmpgiin3j0mngvbua4pa.apps.googleusercontent.com\"\r\n CLIENT_SECRET=\"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\"\r\n REDIRECT_URI=\"http://localhost:8069/auth/google/callback\"\r\n-FRONTEND_URL=\"https://localhost:4200\"\r\n+FRONTEND_URL=\"https://archimanage.systeo.tn:4200\"\r\n GOOGLE_SYSTEM_REFRESH_TOKEN='1//09oB7A4YVsXO1CgYIARAAGAkSNwF-L9IrWlUOUnaPEybbg8OGHXVmdVTqr70WiFMoMSK-8xP349d9rFBJtifwTSXogpc-DILO35M'\r\n # Application Configuration\r\n APP_NAME=EmailService\r\n PORT=8069\r\n"
                },
                {
                    "date": 1749632726628,
                    "content": "Index: \n===================================================================\n--- \n+++ \n@@ -1,7 +1,7 @@\n CLIENT_ID=\"272700212454-9s5a11um6udgkmpgiin3j0mngvbua4pa.apps.googleusercontent.com\"\r\n CLIENT_SECRET=\"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\"\r\n-REDIRECT_URI=\"http://localhost:8069/auth/google/callback\"\r\n+#REDIRECT_URI=\"http://localhost:8069/auth/google/callback\"\r\n FRONTEND_URL=\"https://archimanage.systeo.tn:4200\"\r\n GOOGLE_SYSTEM_REFRESH_TOKEN='1//09oB7A4YVsXO1CgYIARAAGAkSNwF-L9IrWlUOUnaPEybbg8OGHXVmdVTqr70WiFMoMSK-8xP349d9rFBJtifwTSXogpc-DILO35M'\r\n # Application Configuration\r\n APP_NAME=EmailService\r\n"
                },
                {
                    "date": 1749633029688,
                    "content": "Index: \n===================================================================\n--- \n+++ \n@@ -1,7 +1,8 @@\n CLIENT_ID=\"272700212454-9s5a11um6udgkmpgiin3j0mngvbua4pa.apps.googleusercontent.com\"\r\n CLIENT_SECRET=\"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\"\r\n #REDIRECT_URI=\"http://localhost:8069/auth/google/callback\"\r\n+REDIRECT_URI=\"https://e8.systeo.tn/auth/google/callback\"\r\n FRONTEND_URL=\"https://archimanage.systeo.tn:4200\"\r\n GOOGLE_SYSTEM_REFRESH_TOKEN='1//09oB7A4YVsXO1CgYIARAAGAkSNwF-L9IrWlUOUnaPEybbg8OGHXVmdVTqr70WiFMoMSK-8xP349d9rFBJtifwTSXogpc-DILO35M'\r\n # Application Configuration\r\n APP_NAME=EmailService\r\n"
                },
                {
                    "date": 1749633596427,
                    "content": "Index: \n===================================================================\n--- \n+++ \n@@ -1,8 +1,8 @@\n CLIENT_ID=\"272700212454-9s5a11um6udgkmpgiin3j0mngvbua4pa.apps.googleusercontent.com\"\r\n CLIENT_SECRET=\"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\"\r\n #REDIRECT_URI=\"http://localhost:8069/auth/google/callback\"\r\n-REDIRECT_URI=\"https://e8.systeo.tn/auth/google/callback\"\r\n+#REDIRECT_URI=\"https://e8.systeo.tn/auth/google/callback\"\r\n FRONTEND_URL=\"https://archimanage.systeo.tn:4200\"\r\n GOOGLE_SYSTEM_REFRESH_TOKEN='1//09oB7A4YVsXO1CgYIARAAGAkSNwF-L9IrWlUOUnaPEybbg8OGHXVmdVTqr70WiFMoMSK-8xP349d9rFBJtifwTSXogpc-DILO35M'\r\n # Application Configuration\r\n APP_NAME=EmailService\r\n"
                },
                {
                    "date": 1749633603777,
                    "content": "Index: \n===================================================================\n--- \n+++ \n@@ -1,8 +1,8 @@\n CLIENT_ID=\"272700212454-9s5a11um6udgkmpgiin3j0mngvbua4pa.apps.googleusercontent.com\"\r\n CLIENT_SECRET=\"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\"\r\n #REDIRECT_URI=\"http://localhost:8069/auth/google/callback\"\r\n-#REDIRECT_URI=\"https://e8.systeo.tn/auth/google/callback\"\r\n+#focntionne partiellementREDIRECT_URI=\"https://e8.systeo.tn/auth/google/callback\"\r\n FRONTEND_URL=\"https://archimanage.systeo.tn:4200\"\r\n GOOGLE_SYSTEM_REFRESH_TOKEN='1//09oB7A4YVsXO1CgYIARAAGAkSNwF-L9IrWlUOUnaPEybbg8OGHXVmdVTqr70WiFMoMSK-8xP349d9rFBJtifwTSXogpc-DILO35M'\r\n # Application Configuration\r\n APP_NAME=EmailService\r\n"
                },
                {
                    "date": 1749633611347,
                    "content": "Index: \n===================================================================\n--- \n+++ \n@@ -1,8 +1,9 @@\n CLIENT_ID=\"272700212454-9s5a11um6udgkmpgiin3j0mngvbua4pa.apps.googleusercontent.com\"\r\n CLIENT_SECRET=\"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\"\r\n #REDIRECT_URI=\"http://localhost:8069/auth/google/callback\"\r\n-#focntionne partiellementREDIRECT_URI=\"https://e8.systeo.tn/auth/google/callback\"\r\n+#focntionne partiellement REDIRECT_URI=\"https://e8.systeo.tn/auth/google/callback\"\r\n+\r\n FRONTEND_URL=\"https://archimanage.systeo.tn:4200\"\r\n GOOGLE_SYSTEM_REFRESH_TOKEN='1//09oB7A4YVsXO1CgYIARAAGAkSNwF-L9IrWlUOUnaPEybbg8OGHXVmdVTqr70WiFMoMSK-8xP349d9rFBJtifwTSXogpc-DILO35M'\r\n # Application Configuration\r\n APP_NAME=EmailService\r\n"
                },
                {
                    "date": 1749633618654,
                    "content": "Index: \n===================================================================\n--- \n+++ \n@@ -1,9 +1,9 @@\n CLIENT_ID=\"272700212454-9s5a11um6udgkmpgiin3j0mngvbua4pa.apps.googleusercontent.com\"\r\n CLIENT_SECRET=\"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\"\r\n #REDIRECT_URI=\"http://localhost:8069/auth/google/callback\"\r\n #focntionne partiellement REDIRECT_URI=\"https://e8.systeo.tn/auth/google/callback\"\r\n-\r\n+REDIRECT_URI=\"https://archimanage.systeo.tn:8069/auth/google/callback\"\r\n FRONTEND_URL=\"https://archimanage.systeo.tn:4200\"\r\n GOOGLE_SYSTEM_REFRESH_TOKEN='1//09oB7A4YVsXO1CgYIARAAGAkSNwF-L9IrWlUOUnaPEybbg8OGHXVmdVTqr70WiFMoMSK-8xP349d9rFBJtifwTSXogpc-DILO35M'\r\n # Application Configuration\r\n APP_NAME=EmailService\r\n"
                }
            ],
            "date": 1748453006030,
            "name": "Commit-0",
            "content": "CLIENT_ID=272700212454-9s5a11um6udgkmpgiin3j0mngvbua4pa.apps.googleusercontent.com\r\nCLIENT_SECRET=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\r\nREDIRECT_URI=http://localhost:3000/auth/google/callback\r\nFRONTEND_URL=http://localhost:3001\r\nPORT=3000"
        }
    ]
}