{
    "sourceFile": "src/app/shared/project-details/project-details.component.scss",
    "activeCommit": 0,
    "commits": [
        {
            "activePatchIndex": 74,
            "patches": [
                {
                    "date": 1746257287810,
                    "content": "Index: \n===================================================================\n--- \n+++ \n"
                },
                {
                    "date": 1746257301395,
                    "content": "Index: \n===================================================================\n--- \n+++ \n@@ -373,9 +373,9 @@\n   }\r\n }\r\n \r\n // Message affiché s'il n'y a pas de phases\r\n-div[ *ngIf=\"project.phases.length === 0\"] { // Sélecteur plus spécifique si nécessaire\r\n+div { // Sélecteur plus spécifique si nécessaire\r\n   text-align: center;\r\n   padding: $base-padding * 2; // Plus d'espacement\r\n   color: $light-text-color;\r\n   font-style: italic; // Texte en italique\r\n"
                },
                {
                    "date": 1746257320146,
                    "content": "Index: \n===================================================================\n--- \n+++ \n@@ -1,477 +1,273 @@\n-// Variables pour la cohérence du thème\r\n-$primary-color: #E27D60;    // Couleur principale du thème\r\n-$secondary-color: #2787C0;  // Couleur secondaire (ex: indicateur 'plus de membres')\r\n-$text-color: #333;          // Couleur de texte principale\r\n-$light-text-color: #666;   // Couleur de texte plus claire\r\n-$background-color: #F1F1F1; // Couleur de fond générale\r\n-$white-color: #fff;         // Blanc\r\n-$border-color: #ddd;        // Couleur des bordures\r\n-$light-gray: #f9f9f9;       // Gris clair (ex: fond de survol)\r\n-$medium-gray: #ccc;         // Gris moyen\r\n-$dark-gray: #aaa;           // Gris foncé\r\n-$error-color: #d9534f;      // Couleur pour les actions de suppression\r\n-\r\n-$base-padding: 20px;        // Espacement interne de base\r\n-$base-margin: 20px;         // Marge de base\r\n-$border-radius: 10px;       // Rayon de bordure standard\r\n-$card-shadow: 0 4px 8px rgba(0, 0, 0, 0.1); // Ombre portée pour les cartes\r\n-$transition-speed: 0.3s;    // Vitesse de transition pour les animations\r\n-\r\n-// Conteneur principal\r\n .project-details-container {\r\n-  padding: $base-padding;\r\n-  font-family: 'Poppins', sans-serif; // Police de caractères\r\n-  background-color: $background-color;\r\n-  min-height: 95vh; // Hauteur minimale pour occuper l'écran\r\n-  box-sizing: border-box; // Inclut padding et border dans la taille totale\r\n-}\r\n-\r\n-// Style des onglets de navigation\r\n-.tabs {\r\n-  display: flex;\r\n-  margin-bottom: $base-margin;\r\n-  background-color: $white-color;\r\n-  border-radius: $border-radius;\r\n-  overflow: hidden; // Contient les boutons arrondis\r\n-  box-shadow: $card-shadow;\r\n-\r\n-  button {\r\n-    flex: 1; // Chaque bouton prend une part égale de l'espace\r\n-    padding: 15px 10px; // Espacement interne augmenté\r\n+    padding: 20px;\r\n+    font-family: 'Poppins', sans-serif;\r\n+    padding: 20px;\r\n+    background: #F1F1F1;\r\n+  height: 95vh;\r\n+    \r\n+  }\r\n+  \r\n+  .tabs {\r\n+    display: flex;\r\n+    margin-bottom: 20px;\r\n+    \r\n+  }\r\n+  \r\n+  .tabs button {\r\n+    flex: 1;\r\n+    padding: 10px;\r\n     border: none;\r\n-    background-color: $white-color; // Fond par défaut\r\n-    color: $light-text-color;\r\n+    background: #ccc;\r\n     cursor: pointer;\r\n     font-size: 16px;\r\n-    font-weight: 500; // Police légèrement moins grasse\r\n-    text-align: center;\r\n-    transition: background-color $transition-speed ease, color $transition-speed ease;\r\n-    border-bottom: 3px solid transparent; // Bordure inférieure transparente pour l'état actif\r\n-\r\n-    &:hover {\r\n-      background-color: $light-gray; // Fond au survol\r\n-      color: $primary-color; // Couleur du texte au survol\r\n-    }\r\n-\r\n-    // Style de l'onglet actif\r\n-    &.active {\r\n-      background-color: $white-color; // Garde le fond blanc\r\n-      color: $primary-color;\r\n-      font-weight: 600; // Police plus grasse pour l'actif\r\n-      border-bottom-color: $primary-color; // Affiche la bordure inférieure\r\n-    }\r\n   }\r\n-}\r\n-\r\n-// Style de base pour le contenu des onglets\r\n-.tab-content {\r\n-  background-color: $white-color;\r\n-  padding: $base-padding;\r\n-  border-radius: $border-radius;\r\n-  box-shadow: $card-shadow;\r\n-  margin-bottom: $base-margin; // Marge en bas si nécessaire\r\n-}\r\n-\r\n-// Disposition spécifique pour l'onglet \"Détails\"\r\n-.details-content {\r\n-  display: flex;\r\n-  gap: $base-margin; // Espace entre les panneaux gauche et droit\r\n-\r\n-  .left-panel,\r\n-  .right-panel {\r\n-    flex: 1; // Chaque panneau prend la moitié de l'espace\r\n+  \r\n+  .tabs button.active {\r\n+    background: #E27D60;\r\n+    color: white;\r\n   }\r\n-\r\n-  .right-panel {\r\n+  \r\n+  .tab-content {\r\n+    background: white;\r\n+    padding: 20px;\r\n+    border-radius: 20px;\r\n+    \r\n+  }\r\n+  .details-content{\r\n     display: flex;\r\n-    flex-direction: column; // Empile les cartes verticalement\r\n-    gap: $base-margin; // Espace entre les cartes du panneau droit\r\n+  gap: 20px;\r\n   }\r\n-}\r\n-\r\n-// Style des cartes\r\n-.card {\r\n-  background-color: $white-color;\r\n-  padding: $base-padding;\r\n-  border-radius: $border-radius;\r\n-  box-shadow: $card-shadow; // Ombre cohérente\r\n-\r\n-  h2 {\r\n-    margin-top: 0;\r\n-    margin-bottom: 15px;\r\n-    color: $primary-color; // Couleur du titre\r\n-    font-size: 1.2em;\r\n-    border-bottom: 1px solid $border-color; // Ligne de séparation sous le titre\r\n-    padding-bottom: 10px;\r\n+  .left-panel {\r\n+    flex: 1;\r\n   }\r\n-\r\n-  p {\r\n-    margin: 10px 0;\r\n-    color: $light-text-color;\r\n-    line-height: 1.6; // Hauteur de ligne pour la lisibilité\r\n-\r\n-    strong {\r\n-      color: $text-color; // Met en évidence le label\r\n-      margin-right: 5px;\r\n-    }\r\n+  .right-panel {\r\n+    flex: 1;\r\n+    display: flex;\r\n+    flex-direction: column;\r\n+    gap: 20px;\r\n   }\r\n-\r\n-  // Style de la liste (utilisée pour les membres)\r\n-  ul {\r\n-    list-style: none; // Pas de puces\r\n-    padding: 0;\r\n-    margin: 0;\r\n-\r\n-    li {\r\n-      padding: 8px 0;\r\n-      border-bottom: 1px dashed $border-color; // Séparateur en pointillés\r\n-      color: $text-color;\r\n-\r\n-      &:last-child {\r\n-        border-bottom: none; // Pas de bordure pour le dernier élément\r\n-      }\r\n-    }\r\n+  .card {\r\n+    background: white;\r\n+    padding: 20px;\r\n+    border-radius: 10px;\r\n+    box-shadow: 0 4px 8px rgba(0, 0, 0, 0.1);\r\n   }\r\n-}\r\n-\r\n-// Style du bouton \"Modifier\"\r\n-.edit-btn {\r\n-  cursor: pointer;\r\n-  background-color: $primary-color;\r\n-  border-radius: 20px; // Forme de pilule\r\n-  font-weight: 500;\r\n-  min-height: 36px; // Hauteur minimale\r\n-  padding: 8px 20px; // Espacement interne\r\n-  border: none;\r\n-  color: $white-color;\r\n-  margin-top: 15px; // Marge au-dessus\r\n-  transition: background-color $transition-speed ease, transform $transition-speed ease;\r\n-\r\n-  &:hover {\r\n-    background-color: darken($primary-color, 10%); // Assombrit au survol\r\n-    transform: translateY(-2px); // Léger effet de soulèvement\r\n+  \r\n+  .edit-btn {\r\n+    cursor: pointer;\r\n+    background: #E27D60;\r\n+    border-radius: 40px;\r\n+    font-weight: bold;\r\n+    min-height: 2.5rem;\r\n+    padding: 0 1rem;\r\n+    border: none;\r\n+    color: white;\r\n+    margin-top: 10px;\r\n   }\r\n-}\r\n-\r\n-// Style du cercle de progression\r\n-.progress-container {\r\n-  position: relative;\r\n-  width: 120px; // Taille légèrement augmentée\r\n-  height: 120px;\r\n-  margin: 15px auto; // Centré avec marge\r\n-\r\n-  svg {\r\n-    transform: rotate(-90deg); // Fait commencer le cercle en haut\r\n+  \r\n+  .progress-container {\r\n+    position: relative;\r\n+    width: 100px;\r\n+    height: 100px;\r\n+    margin: auto;\r\n   }\r\n-\r\n-  circle {\r\n-    transition: stroke-dashoffset $transition-speed ease; // Animation douce\r\n-  }\r\n-\r\n+  \r\n   .progress-text {\r\n     position: absolute;\r\n     top: 50%;\r\n     left: 50%;\r\n-    transform: translate(-50%, -50%); // Centrage parfait du texte\r\n-    font-size: 1.3em; // Texte plus grand\r\n-    font-weight: 600;\r\n-    color: $primary-color;\r\n+    transform: translate(-50%, -50%);\r\n+    font-size: 18px;\r\n+    font-weight: bold;\r\n   }\r\n-}\r\n-\r\n-// Style de l'en-tête de l'onglet \"Phases\"\r\n-.header {\r\n+  @media (max-width: 768px) {\r\n+    .tab-content {\r\n+      flex-direction: column;\r\n+    }\r\n+  \r\n+    .edit-btn {\r\n+      font-size: 0.9rem;\r\n+    }\r\n+  \r\n+    .progress-container {\r\n+      width: 80px;\r\n+      height: 80px;\r\n+    }\r\n+  \r\n+    .progress-text {\r\n+      font-size: 14px;\r\n+    }\r\n+  }\r\n+ .header {\r\n   display: flex;\r\n   align-items: center;\r\n-  justify-content: space-between; // Espace entre le titre et le bouton\r\n-  margin-bottom: $base-margin; // Espace sous l'en-tête\r\n-  padding-bottom: $base-padding; // Espacement interne en bas\r\n-  border-bottom: 1px solid $border-color; // Ligne de séparation\r\n-\r\n-  h2 {\r\n-    margin: 0; // Supprime la marge par défaut du titre\r\n-    color: $primary-color;\r\n-  }\r\n+  justify-content: space-between; /* Pour que le texte et le bouton soient espacés */\r\n+  width: 100%;\r\n }\r\n \r\n-// Style du bouton \"Ajouter une phase\"\r\n .add-phase {\r\n   cursor: pointer;\r\n-  background-color: $primary-color;\r\n-  border-radius: 25px; // Forme de pilule\r\n-  font-weight: 500;\r\n-  min-height: 40px;\r\n-  padding: 0 25px; // Espacement horizontal\r\n+  background: #E27D60;\r\n+  border-radius: 40px;\r\n+  font-weight: bold;\r\n+  min-height: 3rem;\r\n+  padding: 0 1.5rem; /* Ajout de padding pour rendre le bouton plus large */\r\n   border: none;\r\n-  color: $white-color;\r\n-  display: inline-flex; // Permet l'alignement de l'icône et du texte\r\n+  color: white;\r\n+  display: flex;\r\n   align-items: center;\r\n-  gap: 8px; // Espace entre l'icône et le texte\r\n-  transition: background-color $transition-speed ease, transform $transition-speed ease;\r\n+  justify-content: center;\r\n \r\n   i {\r\n-    font-size: 1.1em; // Icône légèrement plus grande\r\n+    font-size: 1rem; /* Taille de l'icône */\r\n+    font-weight: bold; \r\n+    margin-right: 0.5rem; /* Espacement entre l'icône et le texte */\r\n   }\r\n \r\n-  &:hover {\r\n-    background-color: darken($primary-color, 10%);\r\n-    transform: translateY(-2px); // Effet de soulèvement\r\n+  /* Positionner le bouton à droite avec auto margin */\r\n+  margin-left: auto;\r\n+}\r\n+\r\n+@media (max-width: 768px) {\r\n+  .add-phase {\r\n+    font-size: 0.9rem; /* Réduction de la taille du texte pour les petits écrans */\r\n+    padding: 0.5rem 1rem; /* Ajuster les paddings pour les petits écrans */\r\n   }\r\n+\r\n+  .header {\r\n+    flex-direction: column; /* Aligner les éléments en colonne sur les petits écrans */\r\n+    align-items: flex-start; /* Alignement à gauche pour le texte */\r\n+  }\r\n }\r\n \r\n-// Style du tableau des phases\r\n-.phases-table {\r\n-  width: 100%;\r\n-  overflow-x: auto; // Permet le défilement horizontal sur petits écrans\r\n-  border-radius: $border-radius;\r\n-  box-shadow: $card-shadow;\r\n-  background-color: $white-color;\r\n-\r\n-  table {\r\n+  \r\n+  .phases-table {\r\n     width: 100%;\r\n-    border-collapse: collapse; // Bordures nettes entre les cellules\r\n+    overflow: hidden; \r\n+    border-radius: 12px; \r\n+    box-shadow: 0px 4px 10px rgba(0, 0, 0, 0.1); \r\n+    background: white; \r\n+}\r\n+.phases-table table {\r\n+    width: 100%;\r\n+    border-radius: 12px; \r\n+    overflow: hidden; \r\n+    border-collapse: collapse;\r\n+}\r\n \r\n-    th,\r\n-    td {\r\n-      padding: 15px; // Espacement interne des cellules\r\n-      text-align: left; // Alignement à gauche pour la lisibilité\r\n-      border-bottom: 1px solid $border-color; // Ligne séparatrice horizontale\r\n-      vertical-align: middle; // Alignement vertical au centre\r\n-    }\r\n-\r\n-    th {\r\n-      background-color: $light-gray; // Fond clair pour l'en-tête\r\n-      font-weight: 600; // Texte en gras\r\n-      color: $text-color;\r\n-    }\r\n-\r\n-    td {\r\n-      color: $light-text-color; // Texte plus clair pour les données\r\n-    }\r\n-\r\n-    // Centrage spécifique pour certaines colonnes\r\n-    th:nth-child(4), // Nombre de Tâches\r\n-    td:nth-child(4),\r\n-    th:nth-child(5), // Membres\r\n-    td:nth-child(5),\r\n-    th:nth-child(6), // Actions\r\n-    td:nth-child(6) {\r\n-      text-align: center;\r\n-    }\r\n-\r\n-    tbody tr {\r\n-      cursor: pointer; // Indique que la ligne est cliquable\r\n-      transition: background-color $transition-speed ease;\r\n-\r\n-      &:hover {\r\n-        background-color: lighten($primary-color, 45%); // Effet de survol subtil\r\n-      }\r\n-\r\n-      &:last-child td {\r\n-        border-bottom: none; // Supprime la bordure pour la dernière ligne\r\n-      }\r\n-    }\r\n-  }\r\n+.phases-table th, .phases-table td {\r\n+    padding: 15px;\r\n+    text-align: center;\r\n+    border-bottom: 1px solid #ddd;\r\n }\r\n+tbody{tr{\r\n+    cursor: pointer;\r\n+    transition: background-color 0.3s ease-in-out;\r\n+}}\r\n+.phases-table tr:hover {\r\n+    background-color: #f9f9f9; /* Effet au survol */\r\n+}\r\n+.phases-table th {\r\n+    background-color: #f4f4f4;\r\n+}\r\n \r\n-// Style de l'affichage des membres dans le tableau\r\n .members-container {\r\n   display: flex;\r\n   align-items: center;\r\n-  justify-content: center; // Centre le contenu (images + bouton) dans la cellule\r\n-  gap: 10px; // Espace entre le groupe d'images et le bouton '+'\r\n+  justify-content: center; /* Centre les éléments horizontalement */\r\n+  gap: 10px;\r\n+  width: 100%;\r\n+  \r\n }\r\n \r\n .members {\r\n   display: flex;\r\n   align-items: center;\r\n-  gap: -10px; // Fait se chevaucher légèrement les images\r\n+  justify-content: center;\r\n+  gap: 8px;\r\n+  flex-wrap: nowrap; /* Empêche le retour à la ligne */\r\n+  white-space: nowrap; /* Empêche la rupture du texte */\r\n+  max-width: 100%; /* S'assure que tout reste dans la colonne */\r\n+  overflow: hidden; /* Évite que les éléments débordent */\r\n+}\r\n+.member-option {\r\n+  display: flex;\r\n+  align-items: center;\r\n+  justify-content: space-between;\r\n+  width: 100%;\r\n+  gap: 10px;\r\n+  margin: 8px 0;\r\n+}\r\n+.member-img {\r\n+  width: 32px;\r\n+  height: 32px;\r\n+  border-radius: 50%;\r\n+  object-fit: cover;\r\n+  border: 2px solid #ddd;\r\n \r\n-  .member-img {\r\n-    width: 32px;\r\n-    height: 32px;\r\n-    border-radius: 50%; // Image ronde\r\n-    object-fit: cover; // Assure que l'image couvre la zone\r\n-    border: 2px solid $white-color; // Bordure blanche pour séparer les images qui se chevauchent\r\n-    display: inline-block;\r\n-    background-color: $light-gray; // Fond de secours si l'image ne charge pas\r\n-    box-shadow: 0 0 3px rgba(0, 0, 0, 0.2); // Ombre subtile pour la profondeur\r\n-  }\r\n+}\r\n \r\n-  // Style de l'indicateur \"+X\"\r\n-  .more-members {\r\n-    width: 32px;\r\n-    height: 32px;\r\n-    border-radius: 50%;\r\n-    background-color: $dark-gray; // Fond gris neutre\r\n-    color: $white-color;\r\n-    display: inline-flex; // Utilise inline-flex pour un meilleur contrôle\r\n-    align-items: center;\r\n-    justify-content: center;\r\n-    font-size: 12px; // Petite taille de police\r\n-    font-weight: 600;\r\n-    border: 2px solid $white-color;\r\n-    box-shadow: 0 0 3px rgba(0, 0, 0, 0.2);\r\n-    margin-left: -10px; // Chevauchement avec la dernière image affichée\r\n-    z-index: 1; // S'assure qu'il est au-dessus de l'image précédente\r\n-    flex-shrink: 0; // Empêche le rétrécissement si l'espace manque\r\n-  }\r\n+.more-members {\r\n+  width: 32px;\r\n+  height: 32px;\r\n+  border-radius: 50%;\r\n+  background-color: #b5b5b5;\r\n+  color: white;\r\n+  display: flex;\r\n+  align-items: center;\r\n+  justify-content: center;\r\n+  font-size: 14px;\r\n+  font-weight: bold;\r\n+  flex-shrink: 0; /* Empêche l'élément de se réduire */\r\n }\r\n \r\n-// Style du bouton \"+\" pour ajouter un membre\r\n-.add-member-btn {\r\n-  background: none;\r\n-  border: none;\r\n-  cursor: pointer;\r\n-  padding: 0; // Supprime l'espacement par défaut\r\n-  line-height: 1; // Assure un bon alignement vertical de l'icône\r\n \r\n-  .icon {\r\n-    font-size: 24px; // Icône plus grande\r\n-    color: $secondary-color; // Couleur bleue\r\n-    transition: color $transition-speed ease;\r\n \r\n-    &:hover {\r\n-      color: darken($secondary-color, 15%); // Assombrit au survol\r\n-    }\r\n-  }\r\n-}\r\n \r\n-// Style général pour les boutons d'icônes (Modifier/Supprimer dans le tableau)\r\n-button[mat-icon-button] {\r\n-  background: none;\r\n-  border: none;\r\n-  cursor: pointer;\r\n-  padding: 5px; // Ajoute une zone cliquable autour de l'icône\r\n-  border-radius: 50%; // Rend le fond de survol circulaire\r\n-  transition: background-color $transition-speed ease;\r\n-\r\n-  &:hover {\r\n-    background-color: rgba($dark-gray, 0.1); // Fond très léger au survol\r\n+  \r\n+  button {\r\n+    background: none;\r\n+    border: none;\r\n+    cursor: pointer;\r\n   }\r\n-\r\n-  // Style de base pour les icônes dans ces boutons\r\n+  \r\n   .icon {\r\n     font-size: 18px;\r\n-    color: $text-color; // Couleur par défaut de l'icône\r\n-    transition: color $transition-speed ease;\r\n-    vertical-align: middle; // Aide à l'alignement vertical\r\n+    color: #000000;\r\n   }\r\n-\r\n-  // Changement de couleur de l'icône au survol du bouton\r\n-  &:hover .icon {\r\n-    color: $primary-color;\r\n+  \r\n+  .icon:hover {\r\n+    color: #E27D60;\r\n   }\r\n-\r\n-  // Style spécifique pour l'icône de suppression (poubelle)\r\n-  .bi-trash {\r\n-    color: $error-color; // Rouge pour indiquer une action destructive\r\n+  .bi-trash{\r\n+    color: red;\r\n+    font-size: 18px;\r\n   }\r\n-\r\n-  &:hover .bi-trash {\r\n-    color: darken($error-color, 15%); // Rouge plus foncé au survol\r\n+  .bi-trash:hover{\r\n+    \r\n+    color: rgba(121, 0, 0, 0.638);\r\n   }\r\n-}\r\n \r\n-// Message affiché s'il n'y a pas de phases\r\n-div { // Sélecteur plus spécifique si nécessaire\r\n-  text-align: center;\r\n-  padding: $base-padding * 2; // Plus d'espacement\r\n-  color: $light-text-color;\r\n-  font-style: italic; // Texte en italique\r\n-}\r\n-\r\n-\r\n-// Ajustements pour les écrans plus petits (tablettes)\r\n-@media (max-width: 768px) {\r\n-  .details-content {\r\n-    flex-direction: column; // Empile les panneaux gauche et droit\r\n+  .custom-dialog-container {\r\n+    padding: 20px;\r\n+    border-radius: 8px;\r\n   }\r\n-\r\n-  .header {\r\n-    flex-direction: column; // Empile le titre et le bouton\r\n-    align-items: flex-start; // Aligne les éléments à gauche\r\n-    gap: 15px; // Espace entre le titre et le bouton\r\n-\r\n-    .add-phase {\r\n-      margin-left: 0; // Supprime la marge automatique\r\n-      align-self: flex-start; // Aligne le bouton à gauche\r\n+  \r\n+  @media (max-width: 768px) {\r\n+    .custom-dialog-container {\r\n+      width: 90% !important;  /* Modifie la largeur pour les petits écrans */\r\n+      max-width: 90% !important;\r\n+      left: 5% !important;  /* Centre le modal sur les petits écrans */\r\n+      top: 10% !important;  /* Ajuste la position verticale pour les petits écrans */\r\n     }\r\n   }\r\n-\r\n-  .phases-table {\r\n-    th, td {\r\n-      padding: 12px 10px; // Réduit légèrement l'espacement\r\n-      font-size: 0.9em; // Réduit la taille de la police\r\n+  \r\n+  @media (max-width: 480px) {\r\n+    .custom-dialog-container {\r\n+      width: 95% !important; /* Pour les écrans très petits comme les téléphones */\r\n+      max-width: 95% !important;\r\n+      left: 2.5% !important; /* Centre encore mieux */\r\n+      top: 10% !important;\r\n     }\r\n-\r\n-    // Optionnel: Ajuster l'alignement centré si l'espace est limité\r\n-    // th:nth-child(5), // Membres\r\n-    // td:nth-child(5) {\r\n-    //   text-align: left;\r\n-    // }\r\n   }\r\n-\r\n-  .members-container {\r\n-     justify-content: flex-start; // Aligne les membres à gauche sur petits écrans\r\n-  }\r\n-}\r\n-\r\n-// Ajustements pour les écrans très petits (mobiles)\r\n-@media (max-width: 480px) {\r\n-  .tabs button {\r\n-    font-size: 14px; // Texte des onglets plus petit\r\n-    padding: 12px 5px;\r\n-  }\r\n-\r\n-  .card h2 {\r\n-    font-size: 1.1em; // Titres de carte plus petits\r\n-  }\r\n-\r\n-  // Boutons pleine largeur pour une meilleure accessibilité mobile\r\n-  .edit-btn, .add-phase {\r\n-    width: 100%;\r\n-    text-align: center;\r\n-    padding: 10px 15px;\r\n-    justify-content: center; // Centre le contenu (icône + texte)\r\n-  }\r\n-\r\n-  .phases-table {\r\n-    font-size: 0.85em; // Police encore plus petite pour le tableau\r\n-\r\n-    th, td {\r\n-      padding: 10px 8px; // Espacement réduit\r\n-    }\r\n-  }\r\n-\r\n-  // Optionnel: Masquer des colonnes moins critiques sur mobile\r\n-  // Exemple pour masquer la description :\r\n-  // .phases-table th:nth-child(2),\r\n-  // .phases-table td:nth-child(2) {\r\n-  //   display: none;\r\n-  // }\r\n-}\r\n-\r\n-// Style pour les boîtes de dialogue (conservé de l'original, à adapter si besoin)\r\n-.custom-dialog-container {\r\n-  padding: 20px;\r\n-  border-radius: 8px;\r\n-}\r\n-\r\n-@media (max-width: 768px) {\r\n-  .custom-dialog-container {\r\n-    width: 90% !important;\r\n-    max-width: 90% !important;\r\n-    left: 5% !important; // Centre horizontalement\r\n-    top: 10% !important; // Position verticale\r\n-  }\r\n-}\r\n-\r\n-@media (max-width: 480px) {\r\n-  .custom-dialog-container {\r\n-    width: 95% !important;\r\n-    max-width: 95% !important;\r\n-    left: 2.5% !important; // Centre horizontalement\r\n-    top: 10% !important; // Position verticale\r\n-  }\r\n-}\r\n+  \n\\ No newline at end of file\n"
                },
                {
                    "date": 1746257368073,
                    "content": "Index: \n===================================================================\n--- \n+++ \n@@ -22,9 +22,9 @@\n     font-size: 16px;\r\n   }\r\n   \r\n   .tabs button.active {\r\n-    background: #E27D60;\r\n+    background: #41B3A3;\r\n     color: white;\r\n   }\r\n   \r\n   .tab-content {\r\n@@ -54,9 +54,9 @@\n   }\r\n   \r\n   .edit-btn {\r\n     cursor: pointer;\r\n-    background: #E27D60;\r\n+    background: #41B3A3;\r\n     border-radius: 40px;\r\n     font-weight: bold;\r\n     min-height: 2.5rem;\r\n     padding: 0 1rem;\r\n@@ -106,9 +106,9 @@\n }\r\n \r\n .add-phase {\r\n   cursor: pointer;\r\n-  background: #E27D60;\r\n+  background: #41B3A3;\r\n   border-radius: 40px;\r\n   font-weight: bold;\r\n   min-height: 3rem;\r\n   padding: 0 1.5rem; /* Ajout de padding pour rendre le bouton plus large */\r\n@@ -236,9 +236,9 @@\n     color: #000000;\r\n   }\r\n   \r\n   .icon:hover {\r\n-    color: #E27D60;\r\n+    color: #41B3A3;\r\n   }\r\n   .bi-trash{\r\n     color: red;\r\n     font-size: 18px;\r\n"
                },
                {
                    "date": 1746278286340,
                    "content": "Index: \n===================================================================\n--- \n+++ \n@@ -228,8 +228,25 @@\n   button {\r\n     background: none;\r\n     border: none;\r\n     cursor: pointer;\r\n+    border: none; background: none; cursor: pointer;\r\n+      font-size: 1.2rem; padding: 6px; border-radius: 50%;\r\n+      width: 34px; height: 34px; display: inline-flex;\r\n+      align-items: center; justify-content: center;\r\n+      margin-left: 5px; transition: all 0.2s ease;\r\n+      vertical-align: middle;\r\n+\r\n+      &:disabled { opacity: 0.5; cursor: not-allowed; }\r\n+\r\n+      // Couleurs spécifiques (Utilisant les variables)\r\n+      &.edit-btn { color: $primary-color; &:hover:not(:disabled) { background-color: rgba($primary-color, 0.1); } }\r\n+      &.delete-btn { color: $warn-color; &:hover:not(:disabled) { background-color: rgba($warn-color, 0.1); } }\r\n+      &.save-btn { color: $success-color; &:hover:not(:disabled) { background-color: rgba($success-color, 0.1); } }\r\n+      &.cancel-btn { color: $cancel-color; &:hover:not(:disabled) { background-color: rgba($cancel-color, 0.1); } }\r\n+\r\n+       // Spinner\r\n+       .spinner-border { width: 1em; height: 1em; }\r\n   }\r\n   \r\n   .icon {\r\n     font-size: 18px;\r\n"
                },
                {
                    "date": 1746278310997,
                    "content": "Index: \n===================================================================\n--- \n+++ \n@@ -238,9 +238,9 @@\n \r\n       &:disabled { opacity: 0.5; cursor: not-allowed; }\r\n \r\n       // Couleurs spécifiques (Utilisant les variables)\r\n-      &.edit-btn { color: $primary-color; &:hover:not(:disabled) { background-color: rgba($primary-color, 0.1); } }\r\n+      &.edit-btn { color: #F44336; &:hover:not(:disabled) { background-color: rgba($primary-color, 0.1); } }\r\n       &.delete-btn { color: $warn-color; &:hover:not(:disabled) { background-color: rgba($warn-color, 0.1); } }\r\n       &.save-btn { color: $success-color; &:hover:not(:disabled) { background-color: rgba($success-color, 0.1); } }\r\n       &.cancel-btn { color: $cancel-color; &:hover:not(:disabled) { background-color: rgba($cancel-color, 0.1); } }\r\n \r\n"
                },
                {
                    "date": 1746278336146,
                    "content": "Index: \n===================================================================\n--- \n+++ \n@@ -238,10 +238,10 @@\n \r\n       &:disabled { opacity: 0.5; cursor: not-allowed; }\r\n \r\n       // Couleurs spécifiques (Utilisant les variables)\r\n-      &.edit-btn { color: #F44336; &:hover:not(:disabled) { background-color: rgba($primary-color, 0.1); } }\r\n-      &.delete-btn { color: $warn-color; &:hover:not(:disabled) { background-color: rgba($warn-color, 0.1); } }\r\n+      &.edit-btn { color: #F44336; &:hover:not(:disabled) { background-color: rgba(#F44336, 0.1); } }\r\n+      &.delete-btn { color: #F44336; &:hover:not(:disabled) { background-color: rgba($warn-color, 0.1); } }\r\n       &.save-btn { color: $success-color; &:hover:not(:disabled) { background-color: rgba($success-color, 0.1); } }\r\n       &.cancel-btn { color: $cancel-color; &:hover:not(:disabled) { background-color: rgba($cancel-color, 0.1); } }\r\n \r\n        // Spinner\r\n"
                },
                {
                    "date": 1746278342941,
                    "content": "Index: \n===================================================================\n--- \n+++ \n@@ -239,9 +239,9 @@\n       &:disabled { opacity: 0.5; cursor: not-allowed; }\r\n \r\n       // Couleurs spécifiques (Utilisant les variables)\r\n       &.edit-btn { color: #F44336; &:hover:not(:disabled) { background-color: rgba(#F44336, 0.1); } }\r\n-      &.delete-btn { color: #F44336; &:hover:not(:disabled) { background-color: rgba($warn-color, 0.1); } }\r\n+      &.delete-btn { color: #F44336; &:hover:not(:disabled) { background-color: rgba(#F44336, 0.1); } }\r\n       &.save-btn { color: $success-color; &:hover:not(:disabled) { background-color: rgba($success-color, 0.1); } }\r\n       &.cancel-btn { color: $cancel-color; &:hover:not(:disabled) { background-color: rgba($cancel-color, 0.1); } }\r\n \r\n        // Spinner\r\n"
                },
                {
                    "date": 1746278354861,
                    "content": "Index: \n===================================================================\n--- \n+++ \n@@ -240,9 +240,9 @@\n \r\n       // Couleurs spécifiques (Utilisant les variables)\r\n       &.edit-btn { color: #F44336; &:hover:not(:disabled) { background-color: rgba(#F44336, 0.1); } }\r\n       &.delete-btn { color: #F44336; &:hover:not(:disabled) { background-color: rgba(#F44336, 0.1); } }\r\n-      &.save-btn { color: $success-color; &:hover:not(:disabled) { background-color: rgba($success-color, 0.1); } }\r\n+      &.save-btn { color: $success-color; &:hover:not(:disabled) { background-color: rgba(#4CAF50, 0.1); } }\r\n       &.cancel-btn { color: $cancel-color; &:hover:not(:disabled) { background-color: rgba($cancel-color, 0.1); } }\r\n \r\n        // Spinner\r\n        .spinner-border { width: 1em; height: 1em; }\r\n"
                },
                {
                    "date": 1746278369105,
                    "content": "Index: \n===================================================================\n--- \n+++ \n@@ -240,10 +240,10 @@\n \r\n       // Couleurs spécifiques (Utilisant les variables)\r\n       &.edit-btn { color: #F44336; &:hover:not(:disabled) { background-color: rgba(#F44336, 0.1); } }\r\n       &.delete-btn { color: #F44336; &:hover:not(:disabled) { background-color: rgba(#F44336, 0.1); } }\r\n-      &.save-btn { color: $success-color; &:hover:not(:disabled) { background-color: rgba(#4CAF50, 0.1); } }\r\n-      &.cancel-btn { color: $cancel-color; &:hover:not(:disabled) { background-color: rgba($cancel-color, 0.1); } }\r\n+      &.save-btn { color: #4CAF50; &:hover:not(:disabled) { background-color: rgba(#4CAF50, 0.1); } }\r\n+      &.cancel-btn { color: #6c757d; &:hover:not(:disabled) { background-color: rgba($cancel-color, 0.1); } }\r\n \r\n        // Spinner\r\n        .spinner-border { width: 1em; height: 1em; }\r\n   }\r\n"
                },
                {
                    "date": 1746278401348,
                    "content": "Index: \n===================================================================\n--- \n+++ \n@@ -238,12 +238,12 @@\n \r\n       &:disabled { opacity: 0.5; cursor: not-allowed; }\r\n \r\n       // Couleurs spécifiques (Utilisant les variables)\r\n-      &.edit-btn { color: #F44336; &:hover:not(:disabled) { background-color: rgba(#F44336, 0.1); } }\r\n+      &.edit-btn { color: #41B3A3; &:hover:not(:disabled) { background-color: rgba(#F44336, 0.1); } }\r\n       &.delete-btn { color: #F44336; &:hover:not(:disabled) { background-color: rgba(#F44336, 0.1); } }\r\n       &.save-btn { color: #4CAF50; &:hover:not(:disabled) { background-color: rgba(#4CAF50, 0.1); } }\r\n-      &.cancel-btn { color: #6c757d; &:hover:not(:disabled) { background-color: rgba($cancel-color, 0.1); } }\r\n+      &.cancel-btn { color: #6c757d; &:hover:not(:disabled) { background-color: rgba(#6c757d, 0.1); } }\r\n \r\n        // Spinner\r\n        .spinner-border { width: 1em; height: 1em; }\r\n   }\r\n"
                },
                {
                    "date": 1746278581241,
                    "content": "Index: \n===================================================================\n--- \n+++ \n@@ -228,25 +228,9 @@\n   button {\r\n     background: none;\r\n     border: none;\r\n     cursor: pointer;\r\n-    border: none; background: none; cursor: pointer;\r\n-      font-size: 1.2rem; padding: 6px; border-radius: 50%;\r\n-      width: 34px; height: 34px; display: inline-flex;\r\n-      align-items: center; justify-content: center;\r\n-      margin-left: 5px; transition: all 0.2s ease;\r\n-      vertical-align: middle;\r\n-\r\n-      &:disabled { opacity: 0.5; cursor: not-allowed; }\r\n-\r\n-      // Couleurs spécifiques (Utilisant les variables)\r\n-      &.edit-btn { color: #41B3A3; &:hover:not(:disabled) { background-color: rgba(#F44336, 0.1); } }\r\n-      &.delete-btn { color: #F44336; &:hover:not(:disabled) { background-color: rgba(#F44336, 0.1); } }\r\n-      &.save-btn { color: #4CAF50; &:hover:not(:disabled) { background-color: rgba(#4CAF50, 0.1); } }\r\n-      &.cancel-btn { color: #6c757d; &:hover:not(:disabled) { background-color: rgba(#6c757d, 0.1); } }\r\n-\r\n-       // Spinner\r\n-       .spinner-border { width: 1em; height: 1em; }\r\n+    \r\n   }\r\n   \r\n   .icon {\r\n     font-size: 18px;\r\n"
                },
                {
                    "date": 1746287689047,
                    "content": "Index: \n===================================================================\n--- \n+++ \n@@ -233,9 +233,9 @@\n   }\r\n   \r\n   .icon {\r\n     font-size: 18px;\r\n-    color: #000000;\r\n+    color: #ffffff;\r\n   }\r\n   \r\n   .icon:hover {\r\n     color: #41B3A3;\r\n"
                },
                {
                    "date": 1746350676497,
                    "content": "Index: \n===================================================================\n--- \n+++ \n@@ -1,4 +1,7 @@\n+\r\n+\r\n+\r\n .project-details-container {\r\n     padding: 20px;\r\n     font-family: 'Poppins', sans-serif;\r\n     padding: 20px;\r\n"
                },
                {
                    "date": 1746350686419,
                    "content": "Index: \n===================================================================\n--- \n+++ \n@@ -1,7 +1,23 @@\n \r\n+$primary-color: #41B3A3;\r\n+$accent-color: #E27D60;\r\n+$warn-color: #F44336; // For delete actions\r\n+$success-color: #4CAF50; // For save actions\r\n+$cancel-color: #6c757d; // For cancel actions\r\n \r\n+$text-color-primary: #333;\r\n+$text-color-secondary: #666;\r\n+$text-color-light: #fff;\r\n \r\n+$background-color: #f7f9fc;\r\n+$container-background: #fff;\r\n+$border-color: #e0e0e0;\r\n+$border-radius: 8px;\r\n+$card-shadow: 0 4px 12px rgba(0, 0, 0, 0.08);\r\n+\r\n+\r\n+\r\n .project-details-container {\r\n     padding: 20px;\r\n     font-family: 'Poppins', sans-serif;\r\n     padding: 20px;\r\n"
                },
                {
                    "date": 1746350712478,
                    "content": "Index: \n===================================================================\n--- \n+++ \n@@ -41,9 +41,13 @@\n     font-size: 16px;\r\n   }\r\n   \r\n   .tabs button.active {\r\n-    background: #41B3A3;\r\n+    background-color: $container-background; // Keep background consistent\r\n+    color: $primary-color;\r\n+    font-weight: 600;\r\n+    border-bottom: 3px solid $primary-color; // Use border like in projects header\r\n+\r\n     color: white;\r\n   }\r\n   \r\n   .tab-content {\r\n"
                },
                {
                    "date": 1746350740374,
                    "content": "Index: \n===================================================================\n--- \n+++ \n@@ -53,9 +53,9 @@\n   .tab-content {\r\n     background: white;\r\n     padding: 20px;\r\n     border-radius: 20px;\r\n-    \r\n+    box-shadow: $card-shadow;\r\n   }\r\n   .details-content{\r\n     display: flex;\r\n   gap: 20px;\r\n"
                },
                {
                    "date": 1746350780214,
                    "content": "Index: \n===================================================================\n--- \n+++ \n@@ -123,10 +123,19 @@\n   }\r\n  .header {\r\n   display: flex;\r\n   align-items: center;\r\n-  justify-content: space-between; /* Pour que le texte et le bouton soient espacés */\r\n-  width: 100%;\r\n+  justify-content: space-between;\r\n+  margin-bottom: 24px; // Consistent margin\r\n+  padding-bottom: 16px; // Padding below header content\r\n+  border-bottom: 1px solid $border-color; // Separator line\r\n+\r\n+  h2 {\r\n+    margin: 0;\r\n+    color: $primary-color; // Use primary color for title\r\n+    font-size: 1.5em; // Slightly larger title\r\n+    font-weight: 600;\r\n+  }\r\n }\r\n \r\n .add-phase {\r\n   cursor: pointer;\r\n"
                },
                {
                    "date": 1746350797708,
                    "content": "Index: \n===================================================================\n--- \n+++ \n@@ -138,9 +138,9 @@\n }\r\n \r\n .add-phase {\r\n   cursor: pointer;\r\n-  background: #41B3A3;\r\n+  background-color: $primary-color;\r\n   border-radius: 40px;\r\n   font-weight: bold;\r\n   min-height: 3rem;\r\n   padding: 0 1.5rem; /* Ajout de padding pour rendre le bouton plus large */\r\n"
                },
                {
                    "date": 1746350822351,
                    "content": "Index: \n===================================================================\n--- \n+++ \n@@ -150,11 +150,11 @@\n   align-items: center;\r\n   justify-content: center;\r\n \r\n   i {\r\n-    font-size: 1rem; /* Taille de l'icône */\r\n-    font-weight: bold; \r\n-    margin-right: 0.5rem; /* Espacement entre l'icône et le texte */\r\n+    font-size: 1.1rem; // Consistent icon size\r\n+     font-weight: normal; // Reset font weight if needed\r\n+     margin-right: 8px;\r\n   }\r\n \r\n   /* Positionner le bouton à droite avec auto margin */\r\n   margin-left: auto;\r\n"
                },
                {
                    "date": 1746350866934,
                    "content": "Index: \n===================================================================\n--- \n+++ \n@@ -174,12 +174,13 @@\n \r\n   \r\n   .phases-table {\r\n     width: 100%;\r\n-    overflow: hidden; \r\n-    border-radius: 12px; \r\n-    box-shadow: 0px 4px 10px rgba(0, 0, 0, 0.1); \r\n-    background: white; \r\n+    overflow: hidden; // Important for table border radius within card\r\n+     border-radius: $border-radius; // Use variable\r\n+     box-shadow: $card-shadow; // Use variable\r\n+     background-color: $container-background; // Use variable\r\n+     margin-top: 24px;\r\n }\r\n .phases-table table {\r\n     width: 100%;\r\n     border-radius: 12px; \r\n"
                },
                {
                    "date": 1746350883280,
                    "content": "Index: \n===================================================================\n--- \n+++ \n@@ -182,10 +182,9 @@\n      margin-top: 24px;\r\n }\r\n .phases-table table {\r\n     width: 100%;\r\n-    border-radius: 12px; \r\n-    overflow: hidden; \r\n+    \r\n     border-collapse: collapse;\r\n }\r\n \r\n .phases-table th, .phases-table td {\r\n"
                },
                {
                    "date": 1746350939699,
                    "content": "Index: \n===================================================================\n--- \n+++ \n@@ -191,8 +191,9 @@\n     padding: 15px;\r\n     text-align: center;\r\n     border-bottom: 1px solid #ddd;\r\n }\r\n+\r\n tbody{tr{\r\n     cursor: pointer;\r\n     transition: background-color 0.3s ease-in-out;\r\n }}\r\n"
                },
                {
                    "date": 1746350948511,
                    "content": "Index: \n===================================================================\n--- \n+++ \n@@ -191,9 +191,22 @@\n     padding: 15px;\r\n     text-align: center;\r\n     border-bottom: 1px solid #ddd;\r\n }\r\n-\r\n+// Table Data Cells (td) - Adapted from .data-table td\r\n+.phases-table th {\r\n+  font-size: 12px;\r\n+  font-weight: 600;\r\n+  color: $text-color-secondary;\r\n+  background-color: lighten($background-color, 2%); // Slight background for header\r\n+  border-bottom: 2px solid $border-color; // Thicker bottom border for header\r\n+  text-transform: uppercase;\r\n+  letter-spacing: 0.5px;\r\n+  text-align: left; // Default align left\r\n+  vertical-align: middle;\r\n+  &:not(:first-child):not(:last-child) { text-align: center; } // Center intermediate columns\r\n+  &:last-child { text-align: right; padding-right: 24px; } // Align last column (Actions) right\r\n+}\r\n tbody{tr{\r\n     cursor: pointer;\r\n     transition: background-color 0.3s ease-in-out;\r\n }}\r\n"
                },
                {
                    "date": 1746350973402,
                    "content": "Index: \n===================================================================\n--- \n+++ \n@@ -208,8 +208,10 @@\n }\r\n tbody{tr{\r\n     cursor: pointer;\r\n     transition: background-color 0.3s ease-in-out;\r\n+    &:last-child td { border-bottom: none; } // Remove border from last row cells\r\n+\r\n }}\r\n .phases-table tr:hover {\r\n     background-color: #f9f9f9; /* Effet au survol */\r\n }\r\n"
                },
                {
                    "date": 1746351023192,
                    "content": "Index: \n===================================================================\n--- \n+++ \n@@ -276,9 +276,29 @@\n   button {\r\n     background: none;\r\n     border: none;\r\n     cursor: pointer;\r\n-    \r\n+    &[mat-icon-button] {\r\n+      padding: 6px;\r\n+      border-radius: 50%;\r\n+      width: 34px; // Fixed size\r\n+      height: 34px;\r\n+      display: inline-flex;\r\n+      align-items: center;\r\n+      justify-content: center;\r\n+      margin-left: 4px; // Spacing between buttons\r\n+      transition: background-color 0.2s ease;\r\n+      vertical-align: middle; // Align with text/other elements if needed\r\n+\r\n+      &:hover:not(:disabled) {\r\n+        background-color: rgba($primary-color, 0.1); // Default hover\r\n+      }\r\n+\r\n+      .icon, .bi { // Target icons within the button\r\n+        font-size: 18px; // Consistent icon size\r\n+        color: $text-color-secondary; // Default icon color\r\n+      }\r\n+    }\r\n   }\r\n   \r\n   .icon {\r\n     font-size: 18px;\r\n"
                },
                {
                    "date": 1746351028623,
                    "content": "Index: \n===================================================================\n--- \n+++ \n@@ -301,9 +301,9 @@\n   }\r\n   \r\n   .icon {\r\n     font-size: 18px;\r\n-    color: #ffffff;\r\n+ \r\n   }\r\n   \r\n   .icon:hover {\r\n     color: #41B3A3;\r\n"
                },
                {
                    "date": 1746351046647,
                    "content": "Index: \n===================================================================\n--- \n+++ \n@@ -308,9 +308,9 @@\n   .icon:hover {\r\n     color: #41B3A3;\r\n   }\r\n   .bi-trash{\r\n-    color: red;\r\n+    color: $warn-color;\r\n     font-size: 18px;\r\n   }\r\n   .bi-trash:hover{\r\n     \r\n"
                },
                {
                    "date": 1746351059694,
                    "content": "Index: \n===================================================================\n--- \n+++ \n@@ -311,8 +311,9 @@\n   .bi-trash{\r\n     color: $warn-color;\r\n     font-size: 18px;\r\n   }\r\n+  \r\n   .bi-trash:hover{\r\n     \r\n     color: rgba(121, 0, 0, 0.638);\r\n   }\r\n"
                },
                {
                    "date": 1746351071810,
                    "content": "Index: \n===================================================================\n--- \n+++ \n@@ -311,9 +311,12 @@\n   .bi-trash{\r\n     color: $warn-color;\r\n     font-size: 18px;\r\n   }\r\n-  \r\n+  button[mat-icon-button]:hover:not(:disabled) {\r\n+    &.edit-btn-phase { background-color: rgba($primary-color, 0.1); .icon { color: $primary-color; } }\r\n+    &.delete-btn-phase { background-color: rgba($warn-color, 0.1); .bi-trash { color: darken($warn-color, 10%); } }\r\n+  }\r\n   .bi-trash:hover{\r\n     \r\n     color: rgba(121, 0, 0, 0.638);\r\n   }\r\n"
                },
                {
                    "date": 1746351084752,
                    "content": "Index: \n===================================================================\n--- \n+++ \n@@ -315,8 +315,14 @@\n   button[mat-icon-button]:hover:not(:disabled) {\r\n     &.edit-btn-phase { background-color: rgba($primary-color, 0.1); .icon { color: $primary-color; } }\r\n     &.delete-btn-phase { background-color: rgba($warn-color, 0.1); .bi-trash { color: darken($warn-color, 10%); } }\r\n   }\r\n+  // Style for the \"Add Member\" button (+) in the members column\r\n+  .add-member-btn {\r\n+    // Inherits base button styles, add specifics if needed\r\n+    .icon { color: $primary-color; } // Make the plus icon primary color\r\n+    &:hover { background-color: rgba($primary-color, 0.1); }\r\n+  }\r\n   .bi-trash:hover{\r\n     \r\n     color: rgba(121, 0, 0, 0.638);\r\n   }\r\n"
                },
                {
                    "date": 1746351118088,
                    "content": "Index: \n===================================================================\n--- \n+++ \n@@ -348,5 +348,10 @@\n       left: 2.5% !important; /* Centre encore mieux */\r\n       top: 10% !important;\r\n     }\r\n   }\r\n-  \n\\ No newline at end of file\n+  .members-action-button {\r\n+    // Styles should be similar to .members-action-button in projects.component.scss\r\n+    // Example:\r\n+    color: $primary-color;\r\n+    // ... other styles like padding, border-radius, hover effect ...\r\n++  }\n\\ No newline at end of file\n"
                },
                {
                    "date": 1746351124723,
                    "content": "Index: \n===================================================================\n--- \n+++ \n@@ -352,6 +352,6 @@\n   .members-action-button {\r\n     // Styles should be similar to .members-action-button in projects.component.scss\r\n     // Example:\r\n     color: $primary-color;\r\n-    // ... other styles like padding, border-radius, hover effect ...\r\n-+  }\n\\ No newline at end of file\n+    \r\n+  }\n\\ No newline at end of file\n"
                },
                {
                    "date": 1746351345996,
                    "content": "Index: \n===================================================================\n--- \n+++ \n@@ -308,9 +308,9 @@\n   .icon:hover {\r\n     color: #41B3A3;\r\n   }\r\n   .bi-trash{\r\n-    color: $warn-color;\r\n+    color: $warn-color ;\r\n     font-size: 18px;\r\n   }\r\n   button[mat-icon-button]:hover:not(:disabled) {\r\n     &.edit-btn-phase { background-color: rgba($primary-color, 0.1); .icon { color: $primary-color; } }\r\n@@ -349,9 +349,7 @@\n       top: 10% !important;\r\n     }\r\n   }\r\n   .members-action-button {\r\n-    // Styles should be similar to .members-action-button in projects.component.scss\r\n-    // Example:\r\n     color: $primary-color;\r\n     \r\n   }\n\\ No newline at end of file\n"
                },
                {
                    "date": 1746351558207,
                    "content": "Index: \n===================================================================\n--- \n+++ \n@@ -139,12 +139,8 @@\n \r\n .add-phase {\r\n   cursor: pointer;\r\n   background-color: $primary-color;\r\n-  border-radius: 40px;\r\n-  font-weight: bold;\r\n-  min-height: 3rem;\r\n-  padding: 0 1.5rem; /* Ajout de padding pour rendre le bouton plus large */\r\n   border: none;\r\n   color: white;\r\n   display: flex;\r\n   align-items: center;\r\n@@ -308,9 +304,9 @@\n   .icon:hover {\r\n     color: #41B3A3;\r\n   }\r\n   .bi-trash{\r\n-    color: $warn-color ;\r\n+    color: $warn-color !important ;\r\n     font-size: 18px;\r\n   }\r\n   button[mat-icon-button]:hover:not(:disabled) {\r\n     &.edit-btn-phase { background-color: rgba($primary-color, 0.1); .icon { color: $primary-color; } }\r\n"
                },
                {
                    "date": 1746351568059,
                    "content": "Index: \n===================================================================\n--- \n+++ \n@@ -140,10 +140,9 @@\n .add-phase {\r\n   cursor: pointer;\r\n   background-color: $primary-color;\r\n   border: none;\r\n-  color: white;\r\n-  display: flex;\r\n+  \r\n   align-items: center;\r\n   justify-content: center;\r\n \r\n   i {\r\n"
                },
                {
                    "date": 1746351575645,
                    "content": "Index: \n===================================================================\n--- \n+++ \n@@ -140,9 +140,13 @@\n .add-phase {\r\n   cursor: pointer;\r\n   background-color: $primary-color;\r\n   border: none;\r\n-  \r\n+  color: $text-color-light; // Use variable\r\n+  border-radius: $border-radius; // Match projects button radius (8px)\r\n+  padding: 0 16px; // Match projects button padding\r\n+  min-height: 40px; // Match projects button height\r\n+  display: inline-flex;\r\n   align-items: center;\r\n   justify-content: center;\r\n \r\n   i {\r\n"
                },
                {
                    "date": 1746351585368,
                    "content": "Index: \n===================================================================\n--- \n+++ \n@@ -147,9 +147,14 @@\n   min-height: 40px; // Match projects button height\r\n   display: inline-flex;\r\n   align-items: center;\r\n   justify-content: center;\r\n+  font-size: 14px; // Match projects button font size\r\n+  font-weight: 600; // Match projects button font weight\r\n+  transition: background-color 0.2s ease, box-shadow 0.2s ease, color 0.2s ease; // Match projects button transition\r\n+  box-shadow: 0 1px 3px rgba(0,0,0,0.1); // Match projects button shadow\r\n \r\n+  \r\n   i {\r\n     font-size: 1.1rem; // Consistent icon size\r\n      font-weight: normal; // Reset font weight if needed\r\n      margin-right: 8px;\r\n"
                },
                {
                    "date": 1746351597423,
                    "content": "Index: \n===================================================================\n--- \n+++ \n@@ -154,11 +154,10 @@\n   box-shadow: 0 1px 3px rgba(0,0,0,0.1); // Match projects button shadow\r\n \r\n   \r\n   i {\r\n-    font-size: 1.1rem; // Consistent icon size\r\n-     font-weight: normal; // Reset font weight if needed\r\n-     margin-right: 8px;\r\n+    font-size: 18px; // Match projects button icon size\r\n+    margin-right: 6px;\r\n   }\r\n \r\n   /* Positionner le bouton à droite avec auto margin */\r\n   margin-left: auto;\r\n"
                },
                {
                    "date": 1746351656532,
                    "content": "Index: \n===================================================================\n--- \n+++ \n@@ -292,10 +292,18 @@\n       transition: background-color 0.2s ease;\r\n       vertical-align: middle; // Align with text/other elements if needed\r\n \r\n       &:hover:not(:disabled) {\r\n-        background-color: rgba($primary-color, 0.1); // Default hover\r\n+        box-shadow: 0 2px 6px rgba(0,0,0,0.15);\r\n+        background-color: darken($primary-color, 8%); // Match projects button hover background\r\n       }\r\n+      &:active:not(:disabled) {\r\n+         transform: translateY(1px); // Match projects button active state\r\n+      }\r\n+      &:disabled { // Match projects button disabled state\r\n+        opacity: 0.6;\r\n+        cursor: not-allowed;\r\n+       }\r\n \r\n       .icon, .bi { // Target icons within the button\r\n         font-size: 18px; // Consistent icon size\r\n         color: $text-color-secondary; // Default icon color\r\n"
                },
                {
                    "date": 1746351685782,
                    "content": "Index: \n===================================================================\n--- \n+++ \n@@ -292,18 +292,18 @@\n       transition: background-color 0.2s ease;\r\n       vertical-align: middle; // Align with text/other elements if needed\r\n \r\n       &:hover:not(:disabled) {\r\n-        box-shadow: 0 2px 6px rgba(0,0,0,0.15);\r\n-        background-color: darken($primary-color, 8%); // Match projects button hover background\r\n-      }\r\n-      &:active:not(:disabled) {\r\n-         transform: translateY(1px); // Match projects button active state\r\n-      }\r\n-      &:disabled { // Match projects button disabled state\r\n-        opacity: 0.6;\r\n-        cursor: not-allowed;\r\n-       }\r\n+     box-shadow: 0 2px 6px rgba(0,0,0,0.15);\r\n+     background-color: darken($primary-color, 8%); // Match projects button hover background\r\n+   }\r\n+   &:active:not(:disabled) {\r\n+      transform: translateY(1px); // Match projects button active state\r\n+   }\r\n+   &:disabled { // Match projects button disabled state\r\n+     opacity: 0.6;\r\n+     cursor: not-allowed;\r\n+    }\r\n \r\n       .icon, .bi { // Target icons within the button\r\n         font-size: 18px; // Consistent icon size\r\n         color: $text-color-secondary; // Default icon color\r\n"
                },
                {
                    "date": 1746351691201,
                    "content": "Index: \n===================================================================\n--- \n+++ \n@@ -292,18 +292,10 @@\n       transition: background-color 0.2s ease;\r\n       vertical-align: middle; // Align with text/other elements if needed\r\n \r\n       &:hover:not(:disabled) {\r\n-     box-shadow: 0 2px 6px rgba(0,0,0,0.15);\r\n-     background-color: darken($primary-color, 8%); // Match projects button hover background\r\n-   }\r\n-   &:active:not(:disabled) {\r\n-      transform: translateY(1px); // Match projects button active state\r\n-   }\r\n-   &:disabled { // Match projects button disabled state\r\n-     opacity: 0.6;\r\n-     cursor: not-allowed;\r\n-    }\r\n+        background-color: rgba($primary-color, 0.1); // Default hover\r\n+      }\r\n \r\n       .icon, .bi { // Target icons within the button\r\n         font-size: 18px; // Consistent icon size\r\n         color: $text-color-secondary; // Default icon color\r\n"
                },
                {
                    "date": 1746351703834,
                    "content": "Index: \n===================================================================\n--- \n+++ \n@@ -292,10 +292,18 @@\n       transition: background-color 0.2s ease;\r\n       vertical-align: middle; // Align with text/other elements if needed\r\n \r\n       &:hover:not(:disabled) {\r\n-        background-color: rgba($primary-color, 0.1); // Default hover\r\n-      }\r\n+     box-shadow: 0 2px 6px rgba(0,0,0,0.15);\r\n+     background-color: darken($primary-color, 8%); // Match projects button hover background\r\n+   }\r\n+   &:active:not(:disabled) {\r\n+      transform: translateY(1px); // Match projects button active state\r\n+   }\r\n+   &:disabled { // Match projects button disabled state\r\n+     opacity: 0.6;\r\n+     cursor: not-allowed;\r\n+    }\r\n \r\n       .icon, .bi { // Target icons within the button\r\n         font-size: 18px; // Consistent icon size\r\n         color: $text-color-secondary; // Default icon color\r\n"
                },
                {
                    "date": 1746351751408,
                    "content": "Index: \n===================================================================\n--- \n+++ \n@@ -127,9 +127,9 @@\n   justify-content: space-between;\r\n   margin-bottom: 24px; // Consistent margin\r\n   padding-bottom: 16px; // Padding below header content\r\n   border-bottom: 1px solid $border-color; // Separator line\r\n-\r\n+  color: ;\r\n   h2 {\r\n     margin: 0;\r\n     color: $primary-color; // Use primary color for title\r\n     font-size: 1.5em; // Slightly larger title\r\n"
                },
                {
                    "date": 1746351772213,
                    "content": "Index: \n===================================================================\n--- \n+++ \n@@ -127,9 +127,9 @@\n   justify-content: space-between;\r\n   margin-bottom: 24px; // Consistent margin\r\n   padding-bottom: 16px; // Padding below header content\r\n   border-bottom: 1px solid $border-color; // Separator line\r\n-  color: ;\r\n+  \r\n   h2 {\r\n     margin: 0;\r\n     color: $primary-color; // Use primary color for title\r\n     font-size: 1.5em; // Slightly larger title\r\n"
                },
                {
                    "date": 1746351815383,
                    "content": "Index: \n===================================================================\n--- \n+++ \n@@ -130,9 +130,9 @@\n   border-bottom: 1px solid $border-color; // Separator line\r\n   \r\n   h2 {\r\n     margin: 0;\r\n-    color: $primary-color; // Use primary color for title\r\n+    color: $primary-color !important; // Use primary color for title\r\n     font-size: 1.5em; // Slightly larger title\r\n     font-weight: 600;\r\n   }\r\n }\r\n"
                },
                {
                    "date": 1746351829877,
                    "content": "Index: \n===================================================================\n--- \n+++ \n@@ -130,9 +130,9 @@\n   border-bottom: 1px solid $border-color; // Separator line\r\n   \r\n   h2 {\r\n     margin: 0;\r\n-    color: $primary-color !important; // Use primary color for title\r\n+    color: b; // Use primary color for title\r\n     font-size: 1.5em; // Slightly larger title\r\n     font-weight: 600;\r\n   }\r\n }\r\n"
                },
                {
                    "date": 1746351842890,
                    "content": "Index: \n===================================================================\n--- \n+++ \n@@ -130,9 +130,9 @@\n   border-bottom: 1px solid $border-color; // Separator line\r\n   \r\n   h2 {\r\n     margin: 0;\r\n-    color: b; // Use primary color for title\r\n+    color: $primary-color !important; // Use primary color for title\r\n     font-size: 1.5em; // Slightly larger title\r\n     font-weight: 600;\r\n   }\r\n }\r\n"
                },
                {
                    "date": 1746351923049,
                    "content": "Index: \n===================================================================\n--- \n+++ \n@@ -50,9 +50,9 @@\n     color: white;\r\n   }\r\n   \r\n   .tab-content {\r\n-    background: white;\r\n+    \r\n     padding: 20px;\r\n     border-radius: 20px;\r\n     box-shadow: $card-shadow;\r\n   }\r\n"
                },
                {
                    "date": 1746351932424,
                    "content": "Index: \n===================================================================\n--- \n+++ \n@@ -50,9 +50,9 @@\n     color: white;\r\n   }\r\n   \r\n   .tab-content {\r\n-    \r\n+    background: white;\r\n     padding: 20px;\r\n     border-radius: 20px;\r\n     box-shadow: $card-shadow;\r\n   }\r\n"
                },
                {
                    "date": 1746351949951,
                    "content": "Index: \n===================================================================\n--- \n+++ \n@@ -44,11 +44,9 @@\n   .tabs button.active {\r\n     background-color: $container-background; // Keep background consistent\r\n     color: $primary-color;\r\n     font-weight: 600;\r\n-    border-bottom: 3px solid $primary-color; // Use border like in projects header\r\n-\r\n-    color: white;\r\n+    \r\n   }\r\n   \r\n   .tab-content {\r\n     background: white;\r\n"
                },
                {
                    "date": 1746351956801,
                    "content": "Index: \n===================================================================\n--- \n+++ \n@@ -44,9 +44,11 @@\n   .tabs button.active {\r\n     background-color: $container-background; // Keep background consistent\r\n     color: $primary-color;\r\n     font-weight: 600;\r\n-    \r\n+    border-bottom: 3px solid $primary-color; // Use border like in projects header\r\n+\r\n+    color: white;\r\n   }\r\n   \r\n   .tab-content {\r\n     background: white;\r\n"
                },
                {
                    "date": 1746352007510,
                    "content": "Index: \n===================================================================\n--- \n+++ \n@@ -45,10 +45,8 @@\n     background-color: $container-background; // Keep background consistent\r\n     color: $primary-color;\r\n     font-weight: 600;\r\n     border-bottom: 3px solid $primary-color; // Use border like in projects header\r\n-\r\n-    color: white;\r\n   }\r\n   \r\n   .tab-content {\r\n     background: white;\r\n@@ -140,9 +138,9 @@\n .add-phase {\r\n   cursor: pointer;\r\n   background-color: $primary-color;\r\n   border: none;\r\n-  color: $text-color-light; // Use variable\r\n+  color: $text-color-light !important; // Use variable\r\n   border-radius: $border-radius; // Match projects button radius (8px)\r\n   padding: 0 16px; // Match projects button padding\r\n   min-height: 40px; // Match projects button height\r\n   display: inline-flex;\r\n"
                },
                {
                    "date": 1746352177028,
                    "content": "Index: \n===================================================================\n--- \n+++ \n@@ -206,8 +206,16 @@\n   vertical-align: middle;\r\n   &:not(:first-child):not(:last-child) { text-align: center; } // Center intermediate columns\r\n   &:last-child { text-align: right; padding-right: 24px; } // Align last column (Actions) right\r\n }\r\n+.phases-table td {\r\n+  // Align first two columns (Name, Description) to the left\r\n+  &:nth-child(1),\r\n+  &:nth-child(2) { text-align: left; }\r\n+\r\n+  // Apply ellipsis to the Description column (second column)\r\n+  &:nth-child(2) { white-space: nowrap; overflow: hidden; text-overflow: ellipsis; max-width: 250px; } // Adjust max-width as needed\r\n+}\r\n tbody{tr{\r\n     cursor: pointer;\r\n     transition: background-color 0.3s ease-in-out;\r\n     &:last-child td { border-bottom: none; } // Remove border from last row cells\r\n"
                },
                {
                    "date": 1746352311879,
                    "content": "Index: \n===================================================================\n--- \n+++ \n@@ -213,8 +213,9 @@\n   &:nth-child(2) { text-align: left; }\r\n \r\n   // Apply ellipsis to the Description column (second column)\r\n   &:nth-child(2) { white-space: nowrap; overflow: hidden; text-overflow: ellipsis; max-width: 250px; } // Adjust max-width as needed\r\n+\r\n }\r\n tbody{tr{\r\n     cursor: pointer;\r\n     transition: background-color 0.3s ease-in-out;\r\n"
                },
                {
                    "date": 1746352421039,
                    "content": "Index: \n===================================================================\n--- \n+++ \n@@ -213,8 +213,9 @@\n   &:nth-child(2) { text-align: left; }\r\n \r\n   // Apply ellipsis to the Description column (second column)\r\n   &:nth-child(2) { white-space: nowrap; overflow: hidden; text-overflow: ellipsis; max-width: 250px; } // Adjust max-width as needed\r\n+  &:last-child { text-align: right; white-space: nowrap; padding-right: 16px; } // Match header alignment and prevent wrap\r\n \r\n }\r\n tbody{tr{\r\n     cursor: pointer;\r\n@@ -331,8 +332,9 @@\n     font-size: 18px;\r\n   }\r\n   button[mat-icon-button]:hover:not(:disabled) {\r\n     &.edit-btn-phase { background-color: rgba($primary-color, 0.1); .icon { color: $primary-color; } }\r\n+    \r\n     &.delete-btn-phase { background-color: rgba($warn-color, 0.1); .bi-trash { color: darken($warn-color, 10%); } }\r\n   }\r\n   // Style for the \"Add Member\" button (+) in the members column\r\n   .add-member-btn {\r\n"
                },
                {
                    "date": 1746352427088,
                    "content": "Index: \n===================================================================\n--- \n+++ \n@@ -332,8 +332,9 @@\n     font-size: 18px;\r\n   }\r\n   button[mat-icon-button]:hover:not(:disabled) {\r\n     &.edit-btn-phase { background-color: rgba($primary-color, 0.1); .icon { color: $primary-color; } }\r\n+    &.view-btn-phase { background-color: rgba($primary-color, 0.1); .icon { color: $primary-color; } } // Style for view button hover\r\n     \r\n     &.delete-btn-phase { background-color: rgba($warn-color, 0.1); .bi-trash { color: darken($warn-color, 10%); } }\r\n   }\r\n   // Style for the \"Add Member\" button (+) in the members column\r\n"
                },
                {
                    "date": 1746353205116,
                    "content": "Index: \n===================================================================\n--- \n+++ \n@@ -213,8 +213,9 @@\n   &:nth-child(2) { text-align: left; }\r\n \r\n   // Apply ellipsis to the Description column (second column)\r\n   &:nth-child(2) { white-space: nowrap; overflow: hidden; text-overflow: ellipsis; max-width: 250px; } // Adjust max-width as needed\r\n+  \r\n   &:last-child { text-align: right; white-space: nowrap; padding-right: 16px; } // Match header alignment and prevent wrap\r\n \r\n }\r\n tbody{tr{\r\n@@ -333,9 +334,8 @@\n   }\r\n   button[mat-icon-button]:hover:not(:disabled) {\r\n     &.edit-btn-phase { background-color: rgba($primary-color, 0.1); .icon { color: $primary-color; } }\r\n     &.view-btn-phase { background-color: rgba($primary-color, 0.1); .icon { color: $primary-color; } } // Style for view button hover\r\n-    \r\n     &.delete-btn-phase { background-color: rgba($warn-color, 0.1); .bi-trash { color: darken($warn-color, 10%); } }\r\n   }\r\n   // Style for the \"Add Member\" button (+) in the members column\r\n   .add-member-btn {\r\n"
                },
                {
                    "date": 1746353717345,
                    "content": "Index: \n===================================================================\n--- \n+++ \n@@ -212,10 +212,18 @@\n   &:nth-child(1),\r\n   &:nth-child(2) { text-align: left; }\r\n \r\n   // Apply ellipsis to the Description column (second column)\r\n-  &:nth-child(2) { white-space: nowrap; overflow: hidden; text-overflow: ellipsis; max-width: 250px; } // Adjust max-width as needed\r\n-  \r\n+  &:nth-child(2) { white-space: nowrap; overflow: hidden; text-overflow: ellipsis; max-width: 250px;vertical-align: middle; } // Adjust max-width as needed\r\n+  // Styles for the description cell when its row is expanded\r\n+  &.expanded:nth-child(2) {\r\n+    white-space: normal; // Allow text wrapping\r\n+    overflow: visible;   // Show overflow content\r\n+    text-overflow: clip; // Remove ellipsis\r\n+    max-width: none;     // Remove max-width constraint\r\n+    vertical-align: top; // Align text to top might look better when expanded\r\n+    background-color: lighten($background-color, 1.5%); // Optional: Subtle background highlight\r\n+  }\r\n   &:last-child { text-align: right; white-space: nowrap; padding-right: 16px; } // Match header alignment and prevent wrap\r\n \r\n }\r\n tbody{tr{\r\n"
                },
                {
                    "date": 1746354862950,
                    "content": "Index: \n===================================================================\n--- \n+++ \n@@ -206,8 +206,21 @@\n   vertical-align: middle;\r\n   &:not(:first-child):not(:last-child) { text-align: center; } // Center intermediate columns\r\n   &:last-child { text-align: right; padding-right: 24px; } // Align last column (Actions) right\r\n }\r\n+tr {\r\n+  transition: all 0.3s ease;\r\n+  \r\n+  &.expanded {\r\n+    background-color: rgba(0, 0, 0, 0.02);\r\n+    \r\n+    td {\r\n+      padding-top: 1rem;\r\n+      padding-bottom: 1rem;\r\n+      border-bottom: 1px solid #eee;\r\n+    }\r\n+  }\r\n+}\r\n .phases-table td {\r\n   // Align first two columns (Name, Description) to the left\r\n   &:nth-child(1),\r\n   &:nth-child(2) { text-align: left; }\r\n"
                },
                {
                    "date": 1746354916952,
                    "content": "Index: \n===================================================================\n--- \n+++ \n@@ -393,5 +393,37 @@\n   }\r\n   .members-action-button {\r\n     color: $primary-color;\r\n     \r\n+  }\r\n+\r\n+  .description-container {\r\n+    position: relative;\r\n+  }\r\n+  \r\n+  .description-preview {\r\n+    white-space: nowrap;\r\n+    overflow: hidden;\r\n+    text-overflow: ellipsis;\r\n+    max-width: 250px;\r\n+  }\r\n+  \r\n+  .description-full {\r\n+    white-space: normal;\r\n+    word-break: break-word;\r\n+    padding-top: 0.5rem;\r\n+  }\r\n+  \r\n+  /* Style pour l'icône œil */\r\n+  .bi-eye-slash {\r\n+    color: #666;\r\n+  }\r\n+  \r\n+  /* Animation pour l'expansion */\r\n+  @keyframes fadeIn {\r\n+    from { opacity: 0; max-height: 0; }\r\n+    to { opacity: 1; max-height: 500px; }\r\n+  }\r\n+  \r\n+  .expanded .description-full {\r\n+    animation: fadeIn 0.3s ease-out;\r\n   }\n\\ No newline at end of file\n"
                },
                {
                    "date": 1746355434761,
                    "content": "Index: \n===================================================================\n--- \n+++ \n@@ -225,9 +225,9 @@\n   &:nth-child(1),\r\n   &:nth-child(2) { text-align: left; }\r\n \r\n   // Apply ellipsis to the Description column (second column)\r\n-  &:nth-child(2) { white-space: nowrap; overflow: hidden; text-overflow: ellipsis; max-width: 250px;vertical-align: middle; } // Adjust max-width as needed\r\n+ &:nth-child(2) {  white-space: nowrap; overflow: hidden; text-overflow: ellipsis; max-width: 250px;vertical-align: middle; } // Adjust max-width as needed\r\n   // Styles for the description cell when its row is expanded\r\n   &.expanded:nth-child(2) {\r\n     white-space: normal; // Allow text wrapping\r\n     overflow: visible;   // Show overflow content\r\n"
                },
                {
                    "date": 1746356514120,
                    "content": "Index: \n===================================================================\n--- \n+++ \n@@ -225,9 +225,16 @@\n   &:nth-child(1),\r\n   &:nth-child(2) { text-align: left; }\r\n \r\n   // Apply ellipsis to the Description column (second column)\r\n- &:nth-child(2) {  white-space: nowrap; overflow: hidden; text-overflow: ellipsis; max-width: 250px;vertical-align: middle; } // Adjust max-width as needed\r\n+  &:nth-child(2) {\r\n+    white-space: nowrap;      // Empêche le retour à la ligne\r\n+    overflow: hidden;         // Cache ce qui dépasse\r\n+    text-overflow: ellipsis;  // Ajoute \"...\"\r\n+    max-width: 250px;         // Largeur max avant troncature (ajustez si besoin)\r\n+    vertical-align: middle;   // Alignement vertical par défaut\r\n+    transition: all 0.3s ease; // Ajoute une transition douce\r\n+  }\r\n   // Styles for the description cell when its row is expanded\r\n   &.expanded:nth-child(2) {\r\n     white-space: normal; // Allow text wrapping\r\n     overflow: visible;   // Show overflow content\r\n@@ -235,8 +242,33 @@\n     max-width: none;     // Remove max-width constraint\r\n     vertical-align: top; // Align text to top might look better when expanded\r\n     background-color: lighten($background-color, 1.5%); // Optional: Subtle background highlight\r\n   }\r\n+  .inline-edit-input, .inline-edit-textarea {\r\n+    width: 95%; // Prend presque toute la largeur de la cellule\r\n+    padding: 6px 8px;\r\n+    border: 1px solid $border-color;\r\n+    border-radius: 4px;\r\n+    font-size: inherit; // Garde la taille de police du tableau\r\n+    font-family: inherit;\r\n+    box-sizing: border-box;\r\n+    &:focus {\r\n+      outline: none;\r\n+      border-color: $primary-color;\r\n+      box-shadow: 0 0 0 2px rgba($primary-color, 0.2);\r\n+    }\r\n+  }\r\n+  .inline-edit-textarea {\r\n+    resize: vertical; // Permet le redimensionnement vertical\r\n+    min-height: 40px; // Hauteur minimale\r\n+  }\r\n+  .inline-edit-dates {\r\n+    display: flex;\r\n+    gap: 5px;\r\n+    align-items: center;\r\n+    .date-input { width: auto; } // Ajuste la largeur des inputs date\r\n+  }\r\n+\r\n   &:last-child { text-align: right; white-space: nowrap; padding-right: 16px; } // Match header alignment and prevent wrap\r\n \r\n }\r\n tbody{tr{\r\n"
                },
                {
                    "date": 1746357791296,
                    "content": "Index: \n===================================================================\n--- \n+++ \n@@ -243,11 +243,16 @@\n     vertical-align: top; // Align text to top might look better when expanded\r\n     background-color: lighten($background-color, 1.5%); // Optional: Subtle background highlight\r\n   }\r\n   .inline-edit-input, .inline-edit-textarea {\r\n-    width: 95%; // Prend presque toute la largeur de la cellule\r\n-    padding: 6px 8px;\r\n-    border: 1px solid $border-color;\r\n+    appearance: none;\r\n+    background: transparent;\r\n+    border: none; // Pas de bordure par défaut\r\n+    outline: none; // Pas d'outline par défaut\r\n+\r\n+    width: 100%; // Prend toute la largeur de la cellule\r\n+    padding: 0; // Ajustez si nécessaire pour aligner avec le texte du span\r\n+    margin: 0;\r\n     border-radius: 4px;\r\n     font-size: inherit; // Garde la taille de police du tableau\r\n     font-family: inherit;\r\n     box-sizing: border-box;\r\n"
                },
                {
                    "date": 1746357838874,
                    "content": "Index: \n===================================================================\n--- \n+++ \n@@ -254,8 +254,9 @@\n     margin: 0;\r\n     border-radius: 4px;\r\n     font-size: inherit; // Garde la taille de police du tableau\r\n     font-family: inherit;\r\n+    line-height: inherit; \r\n     box-sizing: border-box;\r\n     &:focus {\r\n       outline: none;\r\n       border-color: $primary-color;\r\n"
                },
                {
                    "date": 1746357845836,
                    "content": "Index: \n===================================================================\n--- \n+++ \n@@ -256,8 +256,9 @@\n     font-size: inherit; // Garde la taille de police du tableau\r\n     font-family: inherit;\r\n     line-height: inherit; \r\n     box-sizing: border-box;\r\n+    border-bottom: 1px dashed $border-color;\r\n     &:focus {\r\n       outline: none;\r\n       border-color: $primary-color;\r\n       box-shadow: 0 0 0 2px rgba($primary-color, 0.2);\r\n"
                },
                {
                    "date": 1746357855927,
                    "content": "Index: \n===================================================================\n--- \n+++ \n@@ -258,11 +258,11 @@\n     line-height: inherit; \r\n     box-sizing: border-box;\r\n     border-bottom: 1px dashed $border-color;\r\n     &:focus {\r\n-      outline: none;\r\n-      border-color: $primary-color;\r\n-      box-shadow: 0 0 0 2px rgba($primary-color, 0.2);\r\n+      border-bottom: 1px solid $primary-color; // Bordure plus visible au focus\r\n+      background-color: lighten($background-color, 2%); // Léger fond au focus\r\n+  \r\n     }\r\n   }\r\n   .inline-edit-textarea {\r\n     resize: vertical; // Permet le redimensionnement vertical\r\n"
                },
                {
                    "date": 1746357868503,
                    "content": "Index: \n===================================================================\n--- \n+++ \n@@ -265,9 +265,11 @@\n     }\r\n   }\r\n   .inline-edit-textarea {\r\n     resize: vertical; // Permet le redimensionnement vertical\r\n-    min-height: 40px; // Hauteur minimale\r\n+    min-height: calc(1em * var(--bs-body-line-height, 1.5)); // Hauteur minimale basée sur la ligne\r\n+    overflow: auto; // Ajoute une barre de défilement si nécessaire\r\n+ \r\n   }\r\n   .inline-edit-dates {\r\n     display: flex;\r\n     gap: 5px;\r\n"
                },
                {
                    "date": 1746358073322,
                    "content": "Index: \n===================================================================\n--- \n+++ \n@@ -247,9 +247,9 @@\n     appearance: none;\r\n     background: transparent;\r\n     border: none; // Pas de bordure par défaut\r\n     outline: none; // Pas d'outline par défaut\r\n-\r\n+    box-shadow: none;\r\n     width: 100%; // Prend toute la largeur de la cellule\r\n     padding: 0; // Ajustez si nécessaire pour aligner avec le texte du span\r\n     margin: 0;\r\n     border-radius: 4px;\r\n"
                },
                {
                    "date": 1746358089800,
                    "content": "Index: \n===================================================================\n--- \n+++ \n@@ -249,9 +249,9 @@\n     border: none; // Pas de bordure par défaut\r\n     outline: none; // Pas d'outline par défaut\r\n     box-shadow: none;\r\n     width: 100%; // Prend toute la largeur de la cellule\r\n-    padding: 0; // Ajustez si nécessaire pour aligner avec le texte du span\r\n+    padding: 1px 2px;// Ajustez si nécessaire pour aligner avec le texte du span\r\n     margin: 0;\r\n     border-radius: 4px;\r\n     font-size: inherit; // Garde la taille de police du tableau\r\n     font-family: inherit;\r\n"
                },
                {
                    "date": 1746358106395,
                    "content": "Index: \n===================================================================\n--- \n+++ \n@@ -255,8 +255,9 @@\n     border-radius: 4px;\r\n     font-size: inherit; // Garde la taille de police du tableau\r\n     font-family: inherit;\r\n     line-height: inherit; \r\n+    color: inherit;\r\n     box-sizing: border-box;\r\n     border-bottom: 1px dashed $border-color;\r\n     &:focus {\r\n       border-bottom: 1px solid $primary-color; // Bordure plus visible au focus\r\n"
                },
                {
                    "date": 1746358125977,
                    "content": "Index: \n===================================================================\n--- \n+++ \n@@ -257,9 +257,9 @@\n     font-family: inherit;\r\n     line-height: inherit; \r\n     color: inherit;\r\n     box-sizing: border-box;\r\n-    border-bottom: 1px dashed $border-color;\r\n+    border-bottom: 1px dashed transparent;\r\n     &:focus {\r\n       border-bottom: 1px solid $primary-color; // Bordure plus visible au focus\r\n       background-color: lighten($background-color, 2%); // Léger fond au focus\r\n   \r\n"
                },
                {
                    "date": 1746358195173,
                    "content": "Index: \n===================================================================\n--- \n+++ \n@@ -261,9 +261,9 @@\n     border-bottom: 1px dashed transparent;\r\n     &:focus {\r\n       border-bottom: 1px solid $primary-color; // Bordure plus visible au focus\r\n       background-color: lighten($background-color, 2%); // Léger fond au focus\r\n-  \r\n+      \r\n     }\r\n   }\r\n   .inline-edit-textarea {\r\n     resize: vertical; // Permet le redimensionnement vertical\r\n"
                },
                {
                    "date": 1746358215466,
                    "content": "Index: \n===================================================================\n--- \n+++ \n@@ -261,14 +261,14 @@\n     border-bottom: 1px dashed transparent;\r\n     &:focus {\r\n       border-bottom: 1px solid $primary-color; // Bordure plus visible au focus\r\n       background-color: lighten($background-color, 2%); // Léger fond au focus\r\n-      \r\n+      outline: none;\r\n     }\r\n   }\r\n   .inline-edit-textarea {\r\n     resize: vertical; // Permet le redimensionnement vertical\r\n-    min-height: calc(1em * var(--bs-body-line-height, 1.5)); // Hauteur minimale basée sur la ligne\r\n+    min-height: auto // Hauteur minimale basée sur la ligne\r\n     overflow: auto; // Ajoute une barre de défilement si nécessaire\r\n  \r\n   }\r\n   .inline-edit-dates {\r\n"
                },
                {
                    "date": 1746358233206,
                    "content": "Index: \n===================================================================\n--- \n+++ \n@@ -266,11 +266,11 @@\n     }\r\n   }\r\n   .inline-edit-textarea {\r\n     resize: vertical; // Permet le redimensionnement vertical\r\n-    min-height: auto // Hauteur minimale basée sur la ligne\r\n+    min-height: auto; // Hauteur minimale basée sur la ligne\r\n     overflow: auto; // Ajoute une barre de défilement si nécessaire\r\n- \r\n+    height: auto;\r\n   }\r\n   .inline-edit-dates {\r\n     display: flex;\r\n     gap: 5px;\r\n"
                }
            ],
            "date": 1746257287810,
            "name": "Commit-0",
            "content": "// Variables pour la cohérence du thème\r\n$primary-color: #E27D60;    // Couleur principale du thème\r\n$secondary-color: #2787C0;  // Couleur secondaire (ex: indicateur 'plus de membres')\r\n$text-color: #333;          // Couleur de texte principale\r\n$light-text-color: #666;   // Couleur de texte plus claire\r\n$background-color: #F1F1F1; // Couleur de fond générale\r\n$white-color: #fff;         // Blanc\r\n$border-color: #ddd;        // Couleur des bordures\r\n$light-gray: #f9f9f9;       // Gris clair (ex: fond de survol)\r\n$medium-gray: #ccc;         // Gris moyen\r\n$dark-gray: #aaa;           // Gris foncé\r\n$error-color: #d9534f;      // Couleur pour les actions de suppression\r\n\r\n$base-padding: 20px;        // Espacement interne de base\r\n$base-margin: 20px;         // Marge de base\r\n$border-radius: 10px;       // Rayon de bordure standard\r\n$card-shadow: 0 4px 8px rgba(0, 0, 0, 0.1); // Ombre portée pour les cartes\r\n$transition-speed: 0.3s;    // Vitesse de transition pour les animations\r\n\r\n// Conteneur principal\r\n.project-details-container {\r\n  padding: $base-padding;\r\n  font-family: 'Poppins', sans-serif; // Police de caractères\r\n  background-color: $background-color;\r\n  min-height: 95vh; // Hauteur minimale pour occuper l'écran\r\n  box-sizing: border-box; // Inclut padding et border dans la taille totale\r\n}\r\n\r\n// Style des onglets de navigation\r\n.tabs {\r\n  display: flex;\r\n  margin-bottom: $base-margin;\r\n  background-color: $white-color;\r\n  border-radius: $border-radius;\r\n  overflow: hidden; // Contient les boutons arrondis\r\n  box-shadow: $card-shadow;\r\n\r\n  button {\r\n    flex: 1; // Chaque bouton prend une part égale de l'espace\r\n    padding: 15px 10px; // Espacement interne augmenté\r\n    border: none;\r\n    background-color: $white-color; // Fond par défaut\r\n    color: $light-text-color;\r\n    cursor: pointer;\r\n    font-size: 16px;\r\n    font-weight: 500; // Police légèrement moins grasse\r\n    text-align: center;\r\n    transition: background-color $transition-speed ease, color $transition-speed ease;\r\n    border-bottom: 3px solid transparent; // Bordure inférieure transparente pour l'état actif\r\n\r\n    &:hover {\r\n      background-color: $light-gray; // Fond au survol\r\n      color: $primary-color; // Couleur du texte au survol\r\n    }\r\n\r\n    // Style de l'onglet actif\r\n    &.active {\r\n      background-color: $white-color; // Garde le fond blanc\r\n      color: $primary-color;\r\n      font-weight: 600; // Police plus grasse pour l'actif\r\n      border-bottom-color: $primary-color; // Affiche la bordure inférieure\r\n    }\r\n  }\r\n}\r\n\r\n// Style de base pour le contenu des onglets\r\n.tab-content {\r\n  background-color: $white-color;\r\n  padding: $base-padding;\r\n  border-radius: $border-radius;\r\n  box-shadow: $card-shadow;\r\n  margin-bottom: $base-margin; // Marge en bas si nécessaire\r\n}\r\n\r\n// Disposition spécifique pour l'onglet \"Détails\"\r\n.details-content {\r\n  display: flex;\r\n  gap: $base-margin; // Espace entre les panneaux gauche et droit\r\n\r\n  .left-panel,\r\n  .right-panel {\r\n    flex: 1; // Chaque panneau prend la moitié de l'espace\r\n  }\r\n\r\n  .right-panel {\r\n    display: flex;\r\n    flex-direction: column; // Empile les cartes verticalement\r\n    gap: $base-margin; // Espace entre les cartes du panneau droit\r\n  }\r\n}\r\n\r\n// Style des cartes\r\n.card {\r\n  background-color: $white-color;\r\n  padding: $base-padding;\r\n  border-radius: $border-radius;\r\n  box-shadow: $card-shadow; // Ombre cohérente\r\n\r\n  h2 {\r\n    margin-top: 0;\r\n    margin-bottom: 15px;\r\n    color: $primary-color; // Couleur du titre\r\n    font-size: 1.2em;\r\n    border-bottom: 1px solid $border-color; // Ligne de séparation sous le titre\r\n    padding-bottom: 10px;\r\n  }\r\n\r\n  p {\r\n    margin: 10px 0;\r\n    color: $light-text-color;\r\n    line-height: 1.6; // Hauteur de ligne pour la lisibilité\r\n\r\n    strong {\r\n      color: $text-color; // Met en évidence le label\r\n      margin-right: 5px;\r\n    }\r\n  }\r\n\r\n  // Style de la liste (utilisée pour les membres)\r\n  ul {\r\n    list-style: none; // Pas de puces\r\n    padding: 0;\r\n    margin: 0;\r\n\r\n    li {\r\n      padding: 8px 0;\r\n      border-bottom: 1px dashed $border-color; // Séparateur en pointillés\r\n      color: $text-color;\r\n\r\n      &:last-child {\r\n        border-bottom: none; // Pas de bordure pour le dernier élément\r\n      }\r\n    }\r\n  }\r\n}\r\n\r\n// Style du bouton \"Modifier\"\r\n.edit-btn {\r\n  cursor: pointer;\r\n  background-color: $primary-color;\r\n  border-radius: 20px; // Forme de pilule\r\n  font-weight: 500;\r\n  min-height: 36px; // Hauteur minimale\r\n  padding: 8px 20px; // Espacement interne\r\n  border: none;\r\n  color: $white-color;\r\n  margin-top: 15px; // Marge au-dessus\r\n  transition: background-color $transition-speed ease, transform $transition-speed ease;\r\n\r\n  &:hover {\r\n    background-color: darken($primary-color, 10%); // Assombrit au survol\r\n    transform: translateY(-2px); // Léger effet de soulèvement\r\n  }\r\n}\r\n\r\n// Style du cercle de progression\r\n.progress-container {\r\n  position: relative;\r\n  width: 120px; // Taille légèrement augmentée\r\n  height: 120px;\r\n  margin: 15px auto; // Centré avec marge\r\n\r\n  svg {\r\n    transform: rotate(-90deg); // Fait commencer le cercle en haut\r\n  }\r\n\r\n  circle {\r\n    transition: stroke-dashoffset $transition-speed ease; // Animation douce\r\n  }\r\n\r\n  .progress-text {\r\n    position: absolute;\r\n    top: 50%;\r\n    left: 50%;\r\n    transform: translate(-50%, -50%); // Centrage parfait du texte\r\n    font-size: 1.3em; // Texte plus grand\r\n    font-weight: 600;\r\n    color: $primary-color;\r\n  }\r\n}\r\n\r\n// Style de l'en-tête de l'onglet \"Phases\"\r\n.header {\r\n  display: flex;\r\n  align-items: center;\r\n  justify-content: space-between; // Espace entre le titre et le bouton\r\n  margin-bottom: $base-margin; // Espace sous l'en-tête\r\n  padding-bottom: $base-padding; // Espacement interne en bas\r\n  border-bottom: 1px solid $border-color; // Ligne de séparation\r\n\r\n  h2 {\r\n    margin: 0; // Supprime la marge par défaut du titre\r\n    color: $primary-color;\r\n  }\r\n}\r\n\r\n// Style du bouton \"Ajouter une phase\"\r\n.add-phase {\r\n  cursor: pointer;\r\n  background-color: $primary-color;\r\n  border-radius: 25px; // Forme de pilule\r\n  font-weight: 500;\r\n  min-height: 40px;\r\n  padding: 0 25px; // Espacement horizontal\r\n  border: none;\r\n  color: $white-color;\r\n  display: inline-flex; // Permet l'alignement de l'icône et du texte\r\n  align-items: center;\r\n  gap: 8px; // Espace entre l'icône et le texte\r\n  transition: background-color $transition-speed ease, transform $transition-speed ease;\r\n\r\n  i {\r\n    font-size: 1.1em; // Icône légèrement plus grande\r\n  }\r\n\r\n  &:hover {\r\n    background-color: darken($primary-color, 10%);\r\n    transform: translateY(-2px); // Effet de soulèvement\r\n  }\r\n}\r\n\r\n// Style du tableau des phases\r\n.phases-table {\r\n  width: 100%;\r\n  overflow-x: auto; // Permet le défilement horizontal sur petits écrans\r\n  border-radius: $border-radius;\r\n  box-shadow: $card-shadow;\r\n  background-color: $white-color;\r\n\r\n  table {\r\n    width: 100%;\r\n    border-collapse: collapse; // Bordures nettes entre les cellules\r\n\r\n    th,\r\n    td {\r\n      padding: 15px; // Espacement interne des cellules\r\n      text-align: left; // Alignement à gauche pour la lisibilité\r\n      border-bottom: 1px solid $border-color; // Ligne séparatrice horizontale\r\n      vertical-align: middle; // Alignement vertical au centre\r\n    }\r\n\r\n    th {\r\n      background-color: $light-gray; // Fond clair pour l'en-tête\r\n      font-weight: 600; // Texte en gras\r\n      color: $text-color;\r\n    }\r\n\r\n    td {\r\n      color: $light-text-color; // Texte plus clair pour les données\r\n    }\r\n\r\n    // Centrage spécifique pour certaines colonnes\r\n    th:nth-child(4), // Nombre de Tâches\r\n    td:nth-child(4),\r\n    th:nth-child(5), // Membres\r\n    td:nth-child(5),\r\n    th:nth-child(6), // Actions\r\n    td:nth-child(6) {\r\n      text-align: center;\r\n    }\r\n\r\n    tbody tr {\r\n      cursor: pointer; // Indique que la ligne est cliquable\r\n      transition: background-color $transition-speed ease;\r\n\r\n      &:hover {\r\n        background-color: lighten($primary-color, 45%); // Effet de survol subtil\r\n      }\r\n\r\n      &:last-child td {\r\n        border-bottom: none; // Supprime la bordure pour la dernière ligne\r\n      }\r\n    }\r\n  }\r\n}\r\n\r\n// Style de l'affichage des membres dans le tableau\r\n.members-container {\r\n  display: flex;\r\n  align-items: center;\r\n  justify-content: center; // Centre le contenu (images + bouton) dans la cellule\r\n  gap: 10px; // Espace entre le groupe d'images et le bouton '+'\r\n}\r\n\r\n.members {\r\n  display: flex;\r\n  align-items: center;\r\n  gap: -10px; // Fait se chevaucher légèrement les images\r\n\r\n  .member-img {\r\n    width: 32px;\r\n    height: 32px;\r\n    border-radius: 50%; // Image ronde\r\n    object-fit: cover; // Assure que l'image couvre la zone\r\n    border: 2px solid $white-color; // Bordure blanche pour séparer les images qui se chevauchent\r\n    display: inline-block;\r\n    background-color: $light-gray; // Fond de secours si l'image ne charge pas\r\n    box-shadow: 0 0 3px rgba(0, 0, 0, 0.2); // Ombre subtile pour la profondeur\r\n  }\r\n\r\n  // Style de l'indicateur \"+X\"\r\n  .more-members {\r\n    width: 32px;\r\n    height: 32px;\r\n    border-radius: 50%;\r\n    background-color: $dark-gray; // Fond gris neutre\r\n    color: $white-color;\r\n    display: inline-flex; // Utilise inline-flex pour un meilleur contrôle\r\n    align-items: center;\r\n    justify-content: center;\r\n    font-size: 12px; // Petite taille de police\r\n    font-weight: 600;\r\n    border: 2px solid $white-color;\r\n    box-shadow: 0 0 3px rgba(0, 0, 0, 0.2);\r\n    margin-left: -10px; // Chevauchement avec la dernière image affichée\r\n    z-index: 1; // S'assure qu'il est au-dessus de l'image précédente\r\n    flex-shrink: 0; // Empêche le rétrécissement si l'espace manque\r\n  }\r\n}\r\n\r\n// Style du bouton \"+\" pour ajouter un membre\r\n.add-member-btn {\r\n  background: none;\r\n  border: none;\r\n  cursor: pointer;\r\n  padding: 0; // Supprime l'espacement par défaut\r\n  line-height: 1; // Assure un bon alignement vertical de l'icône\r\n\r\n  .icon {\r\n    font-size: 24px; // Icône plus grande\r\n    color: $secondary-color; // Couleur bleue\r\n    transition: color $transition-speed ease;\r\n\r\n    &:hover {\r\n      color: darken($secondary-color, 15%); // Assombrit au survol\r\n    }\r\n  }\r\n}\r\n\r\n// Style général pour les boutons d'icônes (Modifier/Supprimer dans le tableau)\r\nbutton[mat-icon-button] {\r\n  background: none;\r\n  border: none;\r\n  cursor: pointer;\r\n  padding: 5px; // Ajoute une zone cliquable autour de l'icône\r\n  border-radius: 50%; // Rend le fond de survol circulaire\r\n  transition: background-color $transition-speed ease;\r\n\r\n  &:hover {\r\n    background-color: rgba($dark-gray, 0.1); // Fond très léger au survol\r\n  }\r\n\r\n  // Style de base pour les icônes dans ces boutons\r\n  .icon {\r\n    font-size: 18px;\r\n    color: $text-color; // Couleur par défaut de l'icône\r\n    transition: color $transition-speed ease;\r\n    vertical-align: middle; // Aide à l'alignement vertical\r\n  }\r\n\r\n  // Changement de couleur de l'icône au survol du bouton\r\n  &:hover .icon {\r\n    color: $primary-color;\r\n  }\r\n\r\n  // Style spécifique pour l'icône de suppression (poubelle)\r\n  .bi-trash {\r\n    color: $error-color; // Rouge pour indiquer une action destructive\r\n  }\r\n\r\n  &:hover .bi-trash {\r\n    color: darken($error-color, 15%); // Rouge plus foncé au survol\r\n  }\r\n}\r\n\r\n// Message affiché s'il n'y a pas de phases\r\ndiv[ *ngIf=\"project.phases.length === 0\"] { // Sélecteur plus spécifique si nécessaire\r\n  text-align: center;\r\n  padding: $base-padding * 2; // Plus d'espacement\r\n  color: $light-text-color;\r\n  font-style: italic; // Texte en italique\r\n}\r\n\r\n\r\n// Ajustements pour les écrans plus petits (tablettes)\r\n@media (max-width: 768px) {\r\n  .details-content {\r\n    flex-direction: column; // Empile les panneaux gauche et droit\r\n  }\r\n\r\n  .header {\r\n    flex-direction: column; // Empile le titre et le bouton\r\n    align-items: flex-start; // Aligne les éléments à gauche\r\n    gap: 15px; // Espace entre le titre et le bouton\r\n\r\n    .add-phase {\r\n      margin-left: 0; // Supprime la marge automatique\r\n      align-self: flex-start; // Aligne le bouton à gauche\r\n    }\r\n  }\r\n\r\n  .phases-table {\r\n    th, td {\r\n      padding: 12px 10px; // Réduit légèrement l'espacement\r\n      font-size: 0.9em; // Réduit la taille de la police\r\n    }\r\n\r\n    // Optionnel: Ajuster l'alignement centré si l'espace est limité\r\n    // th:nth-child(5), // Membres\r\n    // td:nth-child(5) {\r\n    //   text-align: left;\r\n    // }\r\n  }\r\n\r\n  .members-container {\r\n     justify-content: flex-start; // Aligne les membres à gauche sur petits écrans\r\n  }\r\n}\r\n\r\n// Ajustements pour les écrans très petits (mobiles)\r\n@media (max-width: 480px) {\r\n  .tabs button {\r\n    font-size: 14px; // Texte des onglets plus petit\r\n    padding: 12px 5px;\r\n  }\r\n\r\n  .card h2 {\r\n    font-size: 1.1em; // Titres de carte plus petits\r\n  }\r\n\r\n  // Boutons pleine largeur pour une meilleure accessibilité mobile\r\n  .edit-btn, .add-phase {\r\n    width: 100%;\r\n    text-align: center;\r\n    padding: 10px 15px;\r\n    justify-content: center; // Centre le contenu (icône + texte)\r\n  }\r\n\r\n  .phases-table {\r\n    font-size: 0.85em; // Police encore plus petite pour le tableau\r\n\r\n    th, td {\r\n      padding: 10px 8px; // Espacement réduit\r\n    }\r\n  }\r\n\r\n  // Optionnel: Masquer des colonnes moins critiques sur mobile\r\n  // Exemple pour masquer la description :\r\n  // .phases-table th:nth-child(2),\r\n  // .phases-table td:nth-child(2) {\r\n  //   display: none;\r\n  // }\r\n}\r\n\r\n// Style pour les boîtes de dialogue (conservé de l'original, à adapter si besoin)\r\n.custom-dialog-container {\r\n  padding: 20px;\r\n  border-radius: 8px;\r\n}\r\n\r\n@media (max-width: 768px) {\r\n  .custom-dialog-container {\r\n    width: 90% !important;\r\n    max-width: 90% !important;\r\n    left: 5% !important; // Centre horizontalement\r\n    top: 10% !important; // Position verticale\r\n  }\r\n}\r\n\r\n@media (max-width: 480px) {\r\n  .custom-dialog-container {\r\n    width: 95% !important;\r\n    max-width: 95% !important;\r\n    left: 2.5% !important; // Centre horizontalement\r\n    top: 10% !important; // Position verticale\r\n  }\r\n}\r\n"
        }
    ]
}